{"id": 240, "first_name": "Liam", "last_name": "Reidy", "team_id": 6, "previous_games": 0, "previous_average": 0, "previous_total": 0, "feed_id": "1023346", "hs_url": "", "injury_suspension_status": null, "injury_suspension_status_text": null, "predraft_rank": 633, "locked": true, "played_status": {"status": "post", "display": "Played"}, "active": true, "team": {"id": 6, "abbrev": "FRE", "name": "Fremantle"}, "player_match_stats": [{"player_id": 240, "fixture_id": 193, "round": 23, "points": 53, "total_points": 0, "games": 1, "total_games": 0, "minutes_played": 91, "total_minutes_played": 0, "kicks": 2, "total_kicks": 0, "handballs": 4, "total_handballs": 0, "marks": 0, "total_marks": 0, "tackles": 2, "total_tackles": 0, "freekicks_for": 0, "total_freekicks_for": 0, "freekicks_against": 0, "total_freekicks_against": 0, "hitouts": 31, "total_hitouts": 0, "goals": 0, "total_goals": 0, "behinds": 0, "total_behinds": 0, "opp": {"id": 18, "abbrev": "GWS", "name": "GWS Giants"}, "ven": {"id": 17, "name": "Engie Stadium", "display_name": "Engie Stadium", "short_name": "Engie", "abbrev": "ENS"}}, {"player_id": 240, "fixture_id": 207, "round": 24, "points": 29, "total_points": 0, "games": 1, "total_games": 0, "minutes_played": 80, "total_minutes_played": 0, "kicks": 4, "total_kicks": 0, "handballs": 0, "total_handballs": 0, "marks": 0, "total_marks": 0, "tackles": 5, "total_tackles": 0, "freekicks_for": 2, "total_freekicks_for": 0, "freekicks_against": -1, "total_freekicks_against": 0, "hitouts": 19, "total_hitouts": 0, "goals": 0, "total_goals": 0, "behinds": 0, "total_behinds": 0, "opp": {"id": 11, "abbrev": "PTA", "name": "Port Adelaide"}, "ven": {"id": 53, "name": "Perth Stadium", "display_name": "Optus Stadium", "short_name": "Optus", "abbrev": "OS"}}], "player_stats": [{"player_id": 240, "round": 0, "points": 0, "price": 123900, "total_points": 0, "position": 185, "games": 0, "total_games": 0, "price_change": 0, "total_price_change": 0, "last_position": 0, "round_position": 185, "minutes_played": 0, "total_minutes_played": 0, "updated_at": "2024-03-11T23:26:21+11:00", "kicks": 0, "total_kicks": 0, "handballs": 0, "total_handballs": 0, "marks": 0, "total_marks": 0, "tackles": 0, "total_tackles": 0, "freekicks_for": 0, "total_freekicks_for": 0, "freekicks_against": 0, "total_freekicks_against": 0, "hitouts": 0, "total_hitouts": 0, "goals": 0, "total_goals": 0, "behinds": 0, "total_behinds": 0, "avg5": 0, "own_raw": 0, "status": "none", "avg": 0, "std": null, "avg3": 0, "pavg3": 22, "ppts1": 22, "ppts2": 22, "ppts3": 22, "pmin": 22, "pmax": 22, "prange": "22-22", "be1": 22, "be2": 24, "be3": 23, "bp1": null, "bp2": null, "bp3": null, "pp1": 123900, "pp2": 123900, "pp3": 123400, "ppc1": 0, "ppc2": 0, "ppc3": -500, "ppcs": -3100, "capt": 0.00451875, "vice": 0, "own": 0.718, "ownc": 0.718, "ownc3": 0.652478, "owncs": 0.652478, "opp": null, "oppavg": null, "opph": null, "opp1": {"id": 2, "abbrev": "BRL", "name": "Brisbane"}, "opp1avg": 0, "opp1h": 0, "opp2": {"id": 9, "abbrev": "NTH", "name": "North Melbourne"}, "opp2avg": 0, "opp2h": 1, "opp3": {"id": 1, "abbrev": "ADE", "name": "Adelaide"}, "opp3avg": 0, "opp3h": 0, "ven": null, "venavg": 0, "ven1": {"id": 53, "name": "Perth Stadium", "display_name": "Optus Stadium", "short_name": "Optus", "abbrev": "OS"}, "ven1avg": 0, "ven2": {"id": 7, "name": "Docklands Stadium", "display_name": "Marvel Stadium", "short_name": "Marvel", "abbrev": "MARV"}, "ven2avg": 0, "ven3": {"id": 53, "name": "Perth Stadium", "display_name": "Optus Stadium", "short_name": "Optus", "abbrev": "OS"}, "ven3avg": 0, "trin": 27, "trinp": 0.0627119, "trout": 5, "troutp": 0.0116133, "adp": null, "adp_rank": null, "start": 82.7586, "bench": 17.2414, "ownr": 29, "owncr": 29, "owncsr": 0, "livepts": 0, "livegames": 0, "owned": null, "ppts": null, "points_per_min": null, "total_points_per_min": null, "mvp_value": null, "position_change": null, "hot": false, "cold": false, "phot": false, "pcold": false, "position_ranks": [{"pos_rank": "59", "pos_rd_rank": "59", "pos_rank_pos": "RUC"}]}, {"player_id": 240, "round": 1, "points": 0, "price": 123900, "total_points": 0, "position": 432, "games": 0, "total_games": 0, "price_change": 0, "total_price_change": 0, "last_position": 185, "round_position": 415, "minutes_played": 0, "total_minutes_played": 0, "updated_at": "2024-03-17T10:52:24+11:00", "kicks": 0, "total_kicks": 0, "handballs": 0, "total_handballs": 0, "marks": 0, "total_marks": 0, "tackles": 0, "total_tackles": 0, "freekicks_for": 0, "total_freekicks_for": 0, "freekicks_against": 0, "total_freekicks_against": 0, "hitouts": 0, "total_hitouts": 0, "goals": 0, "total_goals": 0, "behinds": 0, "total_behinds": 0, "avg5": 0, "own_raw": 29, "status": "locked", "avg": 0, "std": null, "avg3": 0, "pavg3": 22, "ppts1": 22, "ppts2": 22, "ppts3": 22, "pmin": 22, "pmax": 22, "prange": "22-22", "be1": 23, "be2": 24, "be3": 24, "bp1": null, "bp2": null, "bp3": null, "pp1": 123900, "pp2": 123900, "pp3": 123000, "ppc1": 0, "ppc2": 0, "ppc3": -900, "ppcs": -3900, "capt": 0, "vice": 0, "own": 0.704424, "ownc": 0.638902, "ownc3": 0.638902, "owncs": 0.638902, "opp": {"id": 2, "abbrev": "BRL", "name": "Brisbane", "opposition_ranking": [{"round": 1, "position": "DEF", "avg": 80.4, "rank": 15, "team_id": 2}, {"round": 1, "position": "FWD", "avg": 70.3125, "rank": 17, "team_id": 2}, {"round": 1, "position": "MID", "avg": 76.8125, "rank": 8, "team_id": 2}, {"round": 1, "position": "RUC", "avg": 88.5, "rank": 10, "team_id": 2}]}, "oppavg": 0, "opph": 0, "opp1": {"id": 9, "abbrev": "NTH", "name": "North Melbourne", "opposition_ranking": [{"round": 1, "position": "DEF", "avg": 74, "rank": 9, "team_id": 9}, {"round": 1, "position": "FWD", "avg": 78.1111, "rank": 18, "team_id": 9}, {"round": 1, "position": "MID", "avg": 89.1667, "rank": 16, "team_id": 9}, {"round": 1, "position": "RUC", "avg": 57, "rank": 2, "team_id": 9}]}, "opp1avg": 0, "opp1h": 1, "opp2": {"id": 1, "abbrev": "ADE", "name": "Adelaide", "opposition_ranking": [{"round": 1, "position": "DEF", "avg": 59.8333, "rank": 1, "team_id": 1}, {"round": 1, "position": "FWD", "avg": 60, "rank": 7, "team_id": 1}, {"round": 1, "position": "MID", "avg": 109.286, "rank": 18, "team_id": 1}, {"round": 1, "position": "RUC", "avg": 81, "rank": 8, "team_id": 1}]}, "opp2avg": 0, "opp2h": 0, "opp3": {"id": 3, "abbrev": "CAR", "name": "Carlton", "opposition_ranking": [{"round": 1, "position": "DEF", "avg": 65.125, "rank": 2, "team_id": 3}, {"round": 1, "position": "FWD", "avg": 61.375, "rank": 9, "team_id": 3}, {"round": 1, "position": "MID", "avg": 73.7059, "rank": 7, "team_id": 3}, {"round": 1, "position": "RUC", "avg": 107, "rank": 14, "team_id": 3}]}, "opp3avg": 0, "opp3h": 0, "ven": {"id": 53, "name": "Perth Stadium", "display_name": "Optus Stadium", "short_name": "Optus", "abbrev": "OS"}, "venavg": 0, "ven1": {"id": 7, "name": "Docklands Stadium", "display_name": "Marvel Stadium", "short_name": "Marvel", "abbrev": "MARV"}, "ven1avg": 0, "ven2": {"id": 53, "name": "Perth Stadium", "display_name": "Optus Stadium", "short_name": "Optus", "abbrev": "OS"}, "ven2avg": 0, "ven3": {"id": 1, "name": "Adelaide Oval", "display_name": "Adelaide Oval", "short_name": "Adelaide", "abbrev": "AO"}, "ven3avg": 0, "trin": 20, "trinp": 0.0616105, "trout": 19, "troutp": 0.05853, "adp": null, "adp_rank": null, "start": 72, "bench": 28, "ownr": 25, "owncr": -4, "owncsr": -4, "livepts": 0, "livegames": 0, "owned": 0.718, "ppts": 22, "points_per_min": null, "total_points_per_min": null, "mvp_value": null, "position_change": -247, "hot": false, "cold": false, "phot": false, "pcold": false, "position_ranks": [{"pos_rank": "61", "pos_rd_rank": "61", "pos_rank_pos": "RUC"}]}, {"player_id": 240, "round": 2, "points": 0, "price": 123900, "total_points": 0, "position": 472, "games": 0, "total_games": 0, "price_change": 0, "total_price_change": 0, "last_position": 432, "round_position": 367, "minutes_played": 0, "total_minutes_played": 0, "updated_at": "2024-03-24T10:52:39+11:00", "kicks": 0, "total_kicks": 0, "handballs": 0, "total_handballs": 0, "marks": 0, "total_marks": 0, "tackles": 0, "total_tackles": 0, "freekicks_for": 0, "total_freekicks_for": 0, "freekicks_against": 0, "total_freekicks_against": 0, "hitouts": 0, "total_hitouts": 0, "goals": 0, "total_goals": 0, "behinds": 0, "total_behinds": 0, "avg5": 0, "own_raw": 25, "status": "locked", "avg": 0, "std": null, "avg3": 0, "pavg3": 22, "ppts1": 22, "ppts2": 22, "ppts3": 22, "pmin": 22, "pmax": 22, "prange": "22-22", "be1": 23, "be2": 26, "be3": 26, "bp1": null, "bp2": null, "bp3": null, "pp1": 123900, "pp2": 123900, "pp3": 122000, "ppc1": 0, "ppc2": 0, "ppc3": -1900, "ppcs": -7200, "capt": 0, "vice": 0, "own": 0.553557, "ownc": 0.497777, "ownc3": 0.488035, "owncs": 0.488035, "opp": {"id": 9, "abbrev": "NTH", "name": "North Melbourne", "opposition_ranking": [{"round": 2, "position": "DEF", "avg": 73.6, "rank": 11, "team_id": 9}, {"round": 2, "position": "FWD", "avg": 75.3158, "rank": 18, "team_id": 9}, {"round": 2, "position": "MID", "avg": 85.0769, "rank": 14, "team_id": 9}, {"round": 2, "position": "RUC", "avg": 117.5, "rank": 15, "team_id": 9}]}, "oppavg": 0, "opph": 1, "opp1": {"id": 1, "abbrev": "ADE", "name": "Adelaide", "opposition_ranking": [{"round": 2, "position": "DEF", "avg": 69, "rank": 7, "team_id": 1}, {"round": 2, "position": "FWD", "avg": 66.7778, "rank": 12, "team_id": 1}, {"round": 2, "position": "MID", "avg": 88.25, "rank": 16, "team_id": 1}, {"round": 2, "position": "RUC", "avg": 72, "rank": 3, "team_id": 1}]}, "opp1avg": 0, "opp1h": 0, "opp2": {"id": 3, "abbrev": "CAR", "name": "Carlton", "opposition_ranking": [{"round": 2, "position": "DEF", "avg": 65.125, "rank": 2, "team_id": 3}, {"round": 2, "position": "FWD", "avg": 61.375, "rank": 9, "team_id": 3}, {"round": 2, "position": "MID", "avg": 73.7059, "rank": 5, "team_id": 3}, {"round": 2, "position": "RUC", "avg": 107, "rank": 14, "team_id": 3}]}, "opp2avg": 0, "opp2h": 0, "opp3": {"id": 11, "abbrev": "PTA", "name": "Port Adelaide", "opposition_ranking": [{"round": 2, "position": "DEF", "avg": 68.1765, "rank": 6, "team_id": 11}, {"round": 2, "position": "FWD", "avg": 58.9474, "rank": 6, "team_id": 11}, {"round": 2, "position": "MID", "avg": 62.4615, "rank": 1, "team_id": 11}, {"round": 2, "position": "RUC", "avg": 85.3333, "rank": 7, "team_id": 11}]}, "opp3avg": 0, "opp3h": 1, "ven": {"id": 7, "name": "Docklands Stadium", "display_name": "Marvel Stadium", "short_name": "Marvel", "abbrev": "MARV"}, "venavg": 0, "ven1": {"id": 53, "name": "Perth Stadium", "display_name": "Optus Stadium", "short_name": "Optus", "abbrev": "OS"}, "ven1avg": 0, "ven2": {"id": 1, "name": "Adelaide Oval", "display_name": "Adelaide Oval", "short_name": "Adelaide", "abbrev": "AO"}, "ven2avg": 0, "ven3": {"id": 1, "name": "Adelaide Oval", "display_name": "Adelaide Oval", "short_name": "Adelaide", "abbrev": "AO"}, "ven3avg": 0, "trin": 2, "trinp": 0.006664, "trout": 6, "troutp": 0.019992, "adp": null, "adp_rank": null, "start": 70, "bench": 30, "ownr": 20, "owncr": -5, "owncsr": -9, "livepts": 0, "livegames": 0, "owned": 0.704424, "ppts": 22, "points_per_min": null, "total_points_per_min": null, "mvp_value": null, "position_change": -40, "hot": false, "cold": false, "phot": false, "pcold": false, "position_ranks": [{"pos_rank": "61", "pos_rd_rank": "61", "pos_rank_pos": "RUC"}]}, {"player_id": 240, "round": 3, "points": 0, "price": 123900, "total_points": 0, "position": 490, "games": 0, "total_games": 0, "price_change": 0, "total_price_change": 0, "last_position": 472, "round_position": 369, "minutes_played": 0, "total_minutes_played": 0, "updated_at": "2024-04-01T08:09:21+11:00", "kicks": 0, "total_kicks": 0, "handballs": 0, "total_handballs": 0, "marks": 0, "total_marks": 0, "tackles": 0, "total_tackles": 0, "freekicks_for": 0, "total_freekicks_for": 0, "freekicks_against": 0, "total_freekicks_against": 0, "hitouts": 0, "total_hitouts": 0, "goals": 0, "total_goals": 0, "behinds": 0, "total_behinds": 0, "avg5": 0, "own_raw": 20, "status": "locked", "avg": 0, "std": null, "avg3": 0, "pavg3": 22, "ppts1": 22, "ppts2": 22, "ppts3": 22, "pmin": 22, "pmax": 22, "prange": "22-22", "be1": 24, "be2": 27, "be3": 27, "bp1": null, "bp2": null, "bp3": null, "pp1": 123900, "pp2": 123900, "pp3": 121700, "ppc1": 0, "ppc2": 0, "ppc3": -2200, "ppcs": -8400, "capt": 0, "vice": 0, "own": 0.464735, "ownc": 0.420572, "ownc3": 0.399213, "owncs": 0.399213, "opp": {"id": 1, "abbrev": "ADE", "name": "Adelaide", "opposition_ranking": [{"round": 3, "position": "DEF", "avg": 77.65, "rank": 16, "team_id": 1}, {"round": 3, "position": "FWD", "avg": 66.1429, "rank": 12, "team_id": 1}, {"round": 3, "position": "MID", "avg": 84.9565, "rank": 15, "team_id": 1}, {"round": 3, "position": "RUC", "avg": 78.5, "rank": 6, "team_id": 1}]}, "oppavg": 0, "opph": 0, "opp1": {"id": 3, "abbrev": "CAR", "name": "Carlton", "opposition_ranking": [{"round": 3, "position": "DEF", "avg": 63.4762, "rank": 1, "team_id": 3}, {"round": 3, "position": "FWD", "avg": 60.1923, "rank": 9, "team_id": 3}, {"round": 3, "position": "MID", "avg": 68.0769, "rank": 2, "team_id": 3}, {"round": 3, "position": "RUC", "avg": 101.333, "rank": 13, "team_id": 3}]}, "opp1avg": 0, "opp1h": 0, "opp2": {"id": 11, "abbrev": "PTA", "name": "Port Adelaide", "opposition_ranking": [{"round": 3, "position": "DEF", "avg": 67.75, "rank": 4, "team_id": 11}, {"round": 3, "position": "FWD", "avg": 59.3333, "rank": 8, "team_id": 11}, {"round": 3, "position": "MID", "avg": 67.6316, "rank": 1, "team_id": 11}, {"round": 3, "position": "RUC", "avg": 108.25, "rank": 14, "team_id": 11}]}, "opp2avg": 0, "opp2h": 1, "opp3": {"id": 16, "abbrev": "WCE", "name": "West Coast", "opposition_ranking": [{"round": 3, "position": "DEF", "avg": 88.4286, "rank": 18, "team_id": 16}, {"round": 3, "position": "FWD", "avg": 67.2963, "rank": 14, "team_id": 16}, {"round": 3, "position": "MID", "avg": 88.8261, "rank": 18, "team_id": 16}, {"round": 3, "position": "RUC", "avg": 129.333, "rank": 18, "team_id": 16}]}, "opp3avg": 0, "opp3h": 1, "ven": {"id": 53, "name": "Perth Stadium", "display_name": "Optus Stadium", "short_name": "Optus", "abbrev": "OS"}, "venavg": 0, "ven1": {"id": 1, "name": "Adelaide Oval", "display_name": "Adelaide Oval", "short_name": "Adelaide", "abbrev": "AO"}, "ven1avg": 0, "ven2": {"id": 1, "name": "Adelaide Oval", "display_name": "Adelaide Oval", "short_name": "Adelaide", "abbrev": "AO"}, "ven2avg": 0, "ven3": {"id": 53, "name": "Perth Stadium", "display_name": "Optus Stadium", "short_name": "Optus", "abbrev": "OS"}, "ven3avg": 0, "trin": 0, "trinp": 0, "trout": 2, "troutp": 0.0109975, "adp": null, "adp_rank": null, "start": 64.7059, "bench": 35.2941, "ownr": 17, "owncr": -3, "owncsr": -12, "livepts": 0, "livegames": 0, "owned": 0.553557, "ppts": 22, "points_per_min": null, "total_points_per_min": null, "mvp_value": null, "position_change": -18, "hot": false, "cold": false, "phot": false, "pcold": false, "position_ranks": [{"pos_rank": "61", "pos_rd_rank": "59", "pos_rank_pos": "RUC"}]}, {"player_id": 240, "round": 4, "points": 0, "price": 123900, "total_points": 0, "position": 509, "games": 0, "total_games": 0, "price_change": 0, "total_price_change": 0, "last_position": 490, "round_position": 414, "minutes_played": 0, "total_minutes_played": 0, "updated_at": "2024-04-07T10:09:36+10:00", "kicks": 0, "total_kicks": 0, "handballs": 0, "total_handballs": 0, "marks": 0, "total_marks": 0, "tackles": 0, "total_tackles": 0, "freekicks_for": 0, "total_freekicks_for": 0, "freekicks_against": 0, "total_freekicks_against": 0, "hitouts": 0, "total_hitouts": 0, "goals": 0, "total_goals": 0, "behinds": 0, "total_behinds": 0, "avg5": 0, "own_raw": 17, "status": "locked", "avg": 0, "std": null, "avg3": 0, "pavg3": 22, "ppts1": 22, "ppts2": 22, "ppts3": 22, "pmin": 22, "pmax": 22, "prange": "22-22", "be1": 24, "be2": 27, "be3": 27, "bp1": null, "bp2": null, "bp3": null, "pp1": 123900, "pp2": 123900, "pp3": 121800, "ppc1": 0, "ppc2": 0, "ppc3": -2100, "ppcs": -8100, "capt": 0, "vice": 0, "own": 0.380228, "ownc": 0.342849, "ownc3": 0.324448, "owncs": 0.314706, "opp": {"id": 3, "abbrev": "CAR", "name": "Carlton", "opposition_ranking": [{"round": 4, "position": "DEF", "avg": 64.5714, "rank": 1, "team_id": 3}, {"round": 4, "position": "FWD", "avg": 59.9722, "rank": 8, "team_id": 3}, {"round": 4, "position": "MID", "avg": 72.9697, "rank": 3, "team_id": 3}, {"round": 4, "position": "RUC", "avg": 98.75, "rank": 14, "team_id": 3}]}, "oppavg": 0, "opph": 0, "opp1": {"id": 11, "abbrev": "PTA", "name": "Port Adelaide", "opposition_ranking": [{"round": 4, "position": "DEF", "avg": 66.9375, "rank": 4, "team_id": 11}, {"round": 4, "position": "FWD", "avg": 60.027, "rank": 9, "team_id": 11}, {"round": 4, "position": "MID", "avg": 74.5556, "rank": 7, "team_id": 11}, {"round": 4, "position": "RUC", "avg": 83, "rank": 8, "team_id": 11}]}, "opp1avg": 0, "opp1h": 1, "opp2": {"id": 16, "abbrev": "WCE", "name": "West Coast", "opposition_ranking": [{"round": 4, "position": "DEF", "avg": 79.6333, "rank": 17, "team_id": 16}, {"round": 4, "position": "FWD", "avg": 70.0571, "rank": 17, "team_id": 16}, {"round": 4, "position": "MID", "avg": 84.3125, "rank": 16, "team_id": 16}, {"round": 4, "position": "RUC", "avg": 113.8, "rank": 18, "team_id": 16}]}, "opp2avg": 0, "opp2h": 1, "opp3": {"id": 15, "abbrev": "WBD", "name": "Western Bulldogs", "opposition_ranking": [{"round": 4, "position": "DEF", "avg": 67.8667, "rank": 5, "team_id": 15}, {"round": 4, "position": "FWD", "avg": 59.8333, "rank": 7, "team_id": 15}, {"round": 4, "position": "MID", "avg": 70.4074, "rank": 1, "team_id": 15}, {"round": 4, "position": "RUC", "avg": 101.6, "rank": 16, "team_id": 15}]}, "opp3avg": 0, "opp3h": 0, "ven": {"id": 1, "name": "Adelaide Oval", "display_name": "Adelaide Oval", "short_name": "Adelaide", "abbrev": "AO"}, "venavg": 0, "ven1": {"id": 1, "name": "Adelaide Oval", "display_name": "Adelaide Oval", "short_name": "Adelaide", "abbrev": "AO"}, "ven1avg": 0, "ven2": {"id": 53, "name": "Perth Stadium", "display_name": "Optus Stadium", "short_name": "Optus", "abbrev": "OS"}, "ven2avg": 0, "ven3": {"id": 53, "name": "Perth Stadium", "display_name": "Optus Stadium", "short_name": "Optus", "abbrev": "OS"}, "ven3avg": 0, "trin": 2, "trinp": 0.00708466, "trout": 3, "troutp": 0.010627, "adp": null, "adp_rank": null, "start": 78.5714, "bench": 21.4286, "ownr": 14, "owncr": -3, "owncsr": -15, "livepts": 0, "livegames": 0, "owned": 0.464735, "ppts": 22, "points_per_min": null, "total_points_per_min": null, "mvp_value": null, "position_change": -19, "hot": false, "cold": false, "phot": false, "pcold": false, "position_ranks": [{"pos_rank": "62", "pos_rd_rank": "61", "pos_rank_pos": "RUC"}]}, {"player_id": 240, "round": 5, "points": 0, "price": 123900, "total_points": 0, "position": 522, "games": 0, "total_games": 0, "price_change": 0, "total_price_change": 0, "last_position": 509, "round_position": 0, "minutes_played": 0, "total_minutes_played": 0, "updated_at": "2024-04-21T08:32:32+10:00", "kicks": 0, "total_kicks": 0, "handballs": 0, "total_handballs": 0, "marks": 0, "total_marks": 0, "tackles": 0, "total_tackles": 0, "freekicks_for": 0, "total_freekicks_for": 0, "freekicks_against": 0, "total_freekicks_against": 0, "hitouts": 0, "total_hitouts": 0, "goals": 0, "total_goals": 0, "behinds": 0, "total_behinds": 0, "avg5": 0, "own_raw": 14, "status": "locked", "avg": 0, "std": null, "avg3": 0, "pavg3": 22, "ppts1": 22, "ppts2": 22, "ppts3": 22, "pmin": 22, "pmax": 22, "prange": "22-22", "be1": 23, "be2": 26, "be3": 26, "bp1": null, "bp2": null, "bp3": null, "pp1": 123900, "pp2": 123900, "pp3": 121900, "ppc1": 0, "ppc2": 0, "ppc3": -2000, "ppcs": -7600, "capt": 0, "vice": 0, "own": 0.322754, "ownc": 0.292214, "ownc3": 0.278591, "owncs": 0.257232, "opp": {"id": 11, "abbrev": "PTA", "name": "Port Adelaide", "opposition_ranking": [{"round": 5, "position": "DEF", "avg": 69.4359, "rank": 4, "team_id": 11}, {"round": 5, "position": "FWD", "avg": 60.7391, "rank": 7, "team_id": 11}, {"round": 5, "position": "MID", "avg": 71.6286, "rank": 1, "team_id": 11}, {"round": 5, "position": "RUC", "avg": 81.4286, "rank": 8, "team_id": 11}]}, "oppavg": 0, "opph": 1, "opp1": {"id": 16, "abbrev": "WCE", "name": "West Coast", "opposition_ranking": [{"round": 5, "position": "DEF", "avg": 77.4474, "rank": 18, "team_id": 16}, {"round": 5, "position": "FWD", "avg": 70.8511, "rank": 17, "team_id": 16}, {"round": 5, "position": "MID", "avg": 82, "rank": 13, "team_id": 16}, {"round": 5, "position": "RUC", "avg": 108.429, "rank": 18, "team_id": 16}]}, "opp1avg": 0, "opp1h": 1, "opp2": {"id": 15, "abbrev": "WBD", "name": "Western Bulldogs", "opposition_ranking": [{"round": 5, "position": "DEF", "avg": 68, "rank": 3, "team_id": 15}, {"round": 5, "position": "FWD", "avg": 60.8372, "rank": 8, "team_id": 15}, {"round": 5, "position": "MID", "avg": 74, "rank": 6, "team_id": 15}, {"round": 5, "position": "RUC", "avg": 99.5714, "rank": 16, "team_id": 15}]}, "opp2avg": 0, "opp2h": 0, "opp3": {"id": 12, "abbrev": "RIC", "name": "Richmond", "opposition_ranking": [{"round": 5, "position": "DEF", "avg": 74.125, "rank": 10, "team_id": 12}, {"round": 5, "position": "FWD", "avg": 69.9245, "rank": 16, "team_id": 12}, {"round": 5, "position": "MID", "avg": 87.5, "rank": 18, "team_id": 12}, {"round": 5, "position": "RUC", "avg": 93.1429, "rank": 13, "team_id": 12}]}, "opp3avg": 0, "opp3h": 1, "ven": {"id": 1, "name": "Adelaide Oval", "display_name": "Adelaide Oval", "short_name": "Adelaide", "abbrev": "AO"}, "venavg": 0, "ven1": {"id": 53, "name": "Perth Stadium", "display_name": "Optus Stadium", "short_name": "Optus", "abbrev": "OS"}, "ven1avg": 0, "ven2": {"id": 53, "name": "Perth Stadium", "display_name": "Optus Stadium", "short_name": "Optus", "abbrev": "OS"}, "ven2avg": 0, "ven3": {"id": 13, "name": "Melbourne Cricket Ground", "display_name": "MCG", "short_name": "MCG", "abbrev": "MCG"}, "ven3avg": 0, "trin": 0, "trinp": 0, "trout": 1, "troutp": 0.00378043, "adp": null, "adp_rank": null, "start": 66.6667, "bench": 33.3333, "ownr": 12, "owncr": -2, "owncsr": -17, "livepts": 0, "livegames": 0, "owned": 0.380228, "ppts": 22, "points_per_min": null, "total_points_per_min": null, "mvp_value": null, "position_change": -13, "hot": false, "cold": false, "phot": false, "pcold": false, "position_ranks": [{"pos_rank": "62", "pos_rd_rank": "61", "pos_rank_pos": "RUC"}]}, {"player_id": 240, "round": 6, "points": 0, "price": 123900, "total_points": 0, "position": 532, "games": 0, "total_games": 0, "price_change": 0, "total_price_change": 0, "last_position": 522, "round_position": 368, "minutes_played": 0, "total_minutes_played": 0, "updated_at": "2024-04-21T09:03:02+10:00", "kicks": 0, "total_kicks": 0, "handballs": 0, "total_handballs": 0, "marks": 0, "total_marks": 0, "tackles": 0, "total_tackles": 0, "freekicks_for": 0, "total_freekicks_for": 0, "freekicks_against": 0, "total_freekicks_against": 0, "hitouts": 0, "total_hitouts": 0, "goals": 0, "total_goals": 0, "behinds": 0, "total_behinds": 0, "avg5": 0, "own_raw": 12, "status": "locked", "avg": 0, "std": null, "avg3": 0, "pavg3": 22, "ppts1": 22, "ppts2": 22, "ppts3": 22, "pmin": 22, "pmax": 22, "prange": "22-22", "be1": 24, "be2": 27, "be3": 27, "bp1": null, "bp2": null, "bp3": null, "pp1": 123900, "pp2": 123900, "pp3": 121800, "ppc1": 0, "ppc2": 0, "ppc3": -2100, "ppcs": -8000, "capt": 0, "vice": 0, "own": 0.319404, "ownc": 0.293461, "ownc3": 0.282025, "owncs": 0.253882, "opp": {"id": 16, "abbrev": "WCE", "name": "West Coast", "opposition_ranking": [{"round": 6, "position": "DEF", "avg": 76.2979, "rank": 15, "team_id": 16}, {"round": 6, "position": "FWD", "avg": 69.431, "rank": 17, "team_id": 16}, {"round": 6, "position": "MID", "avg": 78.18, "rank": 12, "team_id": 16}, {"round": 6, "position": "RUC", "avg": 105.667, "rank": 18, "team_id": 16}]}, "oppavg": 0, "opph": 1, "opp1": {"id": 15, "abbrev": "WBD", "name": "Western Bulldogs", "opposition_ranking": [{"round": 6, "position": "DEF", "avg": 68, "rank": 2, "team_id": 15}, {"round": 6, "position": "FWD", "avg": 58.2373, "rank": 4, "team_id": 15}, {"round": 6, "position": "MID", "avg": 75.18, "rank": 7, "team_id": 15}, {"round": 6, "position": "RUC", "avg": 93.5, "rank": 14, "team_id": 15}]}, "opp1avg": 0, "opp1h": 0, "opp2": {"id": 12, "abbrev": "RIC", "name": "Richmond", "opposition_ranking": [{"round": 6, "position": "DEF", "avg": 74.4082, "rank": 14, "team_id": 12}, {"round": 6, "position": "FWD", "avg": 68.8182, "rank": 16, "team_id": 12}, {"round": 6, "position": "MID", "avg": 86.4318, "rank": 18, "team_id": 12}, {"round": 6, "position": "RUC", "avg": 93.1429, "rank": 13, "team_id": 12}]}, "opp2avg": 0, "opp2h": 1, "opp3": {"id": 14, "abbrev": "SYD", "name": "Sydney", "opposition_ranking": [{"round": 6, "position": "DEF", "avg": 73.8571, "rank": 12, "team_id": 14}, {"round": 6, "position": "FWD", "avg": 56.7377, "rank": 1, "team_id": 14}, {"round": 6, "position": "MID", "avg": 73.76, "rank": 4, "team_id": 14}, {"round": 6, "position": "RUC", "avg": 72.9, "rank": 1, "team_id": 14}]}, "opp3avg": 0, "opp3h": 0, "ven": {"id": 53, "name": "Perth Stadium", "display_name": "Optus Stadium", "short_name": "Optus", "abbrev": "OS"}, "venavg": 0, "ven1": {"id": 53, "name": "Perth Stadium", "display_name": "Optus Stadium", "short_name": "Optus", "abbrev": "OS"}, "ven1avg": 0, "ven2": {"id": 13, "name": "Melbourne Cricket Ground", "display_name": "MCG", "short_name": "MCG", "abbrev": "MCG"}, "ven2avg": 0, "ven3": {"id": 53, "name": "Perth Stadium", "display_name": "Optus Stadium", "short_name": "Optus", "abbrev": "OS"}, "ven3avg": 0, "trin": 1, "trinp": 0.00541917, "trout": 2, "troutp": 0.0108383, "adp": null, "adp_rank": null, "start": 75, "bench": 25, "ownr": 12, "owncr": 0, "owncsr": -17, "livepts": 0, "livegames": 0, "owned": 0.322754, "ppts": 22, "points_per_min": null, "total_points_per_min": null, "mvp_value": null, "position_change": -10, "hot": false, "cold": false, "phot": false, "pcold": false, "position_ranks": [{"pos_rank": "67", "pos_rd_rank": "70", "pos_rank_pos": "RUC"}]}, {"player_id": 240, "round": 7, "points": 0, "price": 123900, "total_points": 0, "position": 547, "games": 0, "total_games": 0, "price_change": 0, "total_price_change": 0, "last_position": 532, "round_position": 414, "minutes_played": 0, "total_minutes_played": 0, "updated_at": "2024-04-28T08:47:31+10:00", "kicks": 0, "total_kicks": 0, "handballs": 0, "total_handballs": 0, "marks": 0, "total_marks": 0, "tackles": 0, "total_tackles": 0, "freekicks_for": 0, "total_freekicks_for": 0, "freekicks_against": 0, "total_freekicks_against": 0, "hitouts": 0, "total_hitouts": 0, "goals": 0, "total_goals": 0, "behinds": 0, "total_behinds": 0, "avg5": 0, "own_raw": 12, "status": "locked", "avg": 0, "std": null, "avg3": 0, "pavg3": 22, "ppts1": 22, "ppts2": 22, "ppts3": 22, "pmin": 22, "pmax": 22, "prange": "22-22", "be1": 24, "be2": 27, "be3": 27, "bp1": null, "bp2": null, "bp3": null, "pp1": 123900, "pp2": 123900, "pp3": 121700, "ppc1": 0, "ppc2": 0, "ppc3": -2200, "ppcs": -8400, "capt": 0, "vice": 0, "own": 0.290161, "ownc": 0.264413, "ownc3": 0.259621, "owncs": 0.224639, "opp": {"id": 15, "abbrev": "WBD", "name": "Western Bulldogs", "opposition_ranking": [{"round": 7, "position": "DEF", "avg": 68.6613, "rank": 2, "team_id": 15}, {"round": 7, "position": "FWD", "avg": 59.5507, "rank": 5, "team_id": 15}, {"round": 7, "position": "MID", "avg": 77, "rank": 9, "team_id": 15}, {"round": 7, "position": "RUC", "avg": 93.1, "rank": 13, "team_id": 15}]}, "oppavg": 0, "opph": 0, "opp1": {"id": 12, "abbrev": "RIC", "name": "Richmond", "opposition_ranking": [{"round": 7, "position": "DEF", "avg": 75.5082, "rank": 15, "team_id": 12}, {"round": 7, "position": "FWD", "avg": 66.3571, "rank": 15, "team_id": 12}, {"round": 7, "position": "MID", "avg": 86.8868, "rank": 18, "team_id": 12}, {"round": 7, "position": "RUC", "avg": 101.75, "rank": 17, "team_id": 12}]}, "opp1avg": 0, "opp1h": 1, "opp2": {"id": 14, "abbrev": "SYD", "name": "Sydney", "opposition_ranking": [{"round": 7, "position": "DEF", "avg": 71.5085, "rank": 8, "team_id": 14}, {"round": 7, "position": "FWD", "avg": 55.3611, "rank": 1, "team_id": 14}, {"round": 7, "position": "MID", "avg": 73, "rank": 4, "team_id": 14}, {"round": 7, "position": "RUC", "avg": 75.9091, "rank": 2, "team_id": 14}]}, "opp2avg": 0, "opp2h": 0, "opp3": {"id": 13, "abbrev": "STK", "name": "St Kilda", "opposition_ranking": [{"round": 7, "position": "DEF", "avg": 79.5614, "rank": 18, "team_id": 13}, {"round": 7, "position": "FWD", "avg": 65.2239, "rank": 14, "team_id": 13}, {"round": 7, "position": "MID", "avg": 76.9333, "rank": 8, "team_id": 13}, {"round": 7, "position": "RUC", "avg": 85.1818, "rank": 9, "team_id": 13}]}, "opp3avg": 0, "opp3h": 1, "ven": {"id": 53, "name": "Perth Stadium", "display_name": "Optus Stadium", "short_name": "Optus", "abbrev": "OS"}, "venavg": 0, "ven1": {"id": 13, "name": "Melbourne Cricket Ground", "display_name": "MCG", "short_name": "MCG", "abbrev": "MCG"}, "ven1avg": 0, "ven2": {"id": 53, "name": "Perth Stadium", "display_name": "Optus Stadium", "short_name": "Optus", "abbrev": "OS"}, "ven2avg": 0, "ven3": {"id": 7, "name": "Docklands Stadium", "display_name": "Marvel Stadium", "short_name": "Marvel", "abbrev": "MARV"}, "ven3avg": 0, "trin": 0, "trinp": 0, "trout": 2, "troutp": 0.0109337, "adp": null, "adp_rank": null, "start": 81.8182, "bench": 18.1818, "ownr": 11, "owncr": -1, "owncsr": -18, "livepts": 0, "livegames": 0, "owned": 0.319404, "ppts": 22, "points_per_min": null, "total_points_per_min": null, "mvp_value": null, "position_change": -15, "hot": false, "cold": false, "phot": false, "pcold": false, "position_ranks": [{"pos_rank": "56", "pos_rd_rank": "59", "pos_rank_pos": "RUC"}]}, {"player_id": 240, "round": 8, "points": 0, "price": 123900, "total_points": 0, "position": 559, "games": 0, "total_games": 0, "price_change": 0, "total_price_change": 0, "last_position": 547, "round_position": 412, "minutes_played": 0, "total_minutes_played": 0, "updated_at": "2024-05-05T12:13:28+10:00", "kicks": 0, "total_kicks": 0, "handballs": 0, "total_handballs": 0, "marks": 0, "total_marks": 0, "tackles": 0, "total_tackles": 0, "freekicks_for": 0, "total_freekicks_for": 0, "freekicks_against": 0, "total_freekicks_against": 0, "hitouts": 0, "total_hitouts": 0, "goals": 0, "total_goals": 0, "behinds": 0, "total_behinds": 0, "avg5": 0, "own_raw": 11, "status": "locked", "avg": 0, "std": null, "avg3": 0, "pavg3": 22, "ppts1": 22, "ppts2": 22, "ppts3": 22, "pmin": 22, "pmax": 22, "prange": "22-22", "be1": 23, "be2": 26, "be3": 26, "bp1": null, "bp2": null, "bp3": null, "pp1": 123900, "pp2": 123900, "pp3": 121900, "ppc1": 0, "ppc2": 0, "ppc3": -2000, "ppcs": -7600, "capt": 0, "vice": 0, "own": 0.366492, "ownc": 0.343048, "ownc3": 0.34055, "owncs": 0.30097, "opp": {"id": 12, "abbrev": "RIC", "name": "Richmond", "opposition_ranking": [{"round": 8, "position": "DEF", "avg": 77.5072, "rank": 18, "team_id": 12}, {"round": 8, "position": "FWD", "avg": 65.4557, "rank": 16, "team_id": 12}, {"round": 8, "position": "MID", "avg": 86.5484, "rank": 18, "team_id": 12}, {"round": 8, "position": "RUC", "avg": 97.9, "rank": 16, "team_id": 12}]}, "oppavg": 0, "opph": 1, "opp1": {"id": 14, "abbrev": "SYD", "name": "Sydney", "opposition_ranking": [{"round": 8, "position": "DEF", "avg": 72.4848, "rank": 9, "team_id": 14}, {"round": 8, "position": "FWD", "avg": 55.6341, "rank": 1, "team_id": 14}, {"round": 8, "position": "MID", "avg": 73.2121, "rank": 2, "team_id": 14}, {"round": 8, "position": "RUC", "avg": 76.9167, "rank": 3, "team_id": 14}]}, "opp1avg": 0, "opp1h": 0, "opp2": {"id": 13, "abbrev": "STK", "name": "St Kilda", "opposition_ranking": [{"round": 8, "position": "DEF", "avg": 77.0149, "rank": 16, "team_id": 13}, {"round": 8, "position": "FWD", "avg": 63.4675, "rank": 14, "team_id": 13}, {"round": 8, "position": "MID", "avg": 76.4493, "rank": 10, "team_id": 13}, {"round": 8, "position": "RUC", "avg": 89.1667, "rank": 12, "team_id": 13}]}, "opp2avg": 0, "opp2h": 1, "opp3": {"id": 4, "abbrev": "COL", "name": "Collingwood", "opposition_ranking": [{"round": 8, "position": "DEF", "avg": 75.0923, "rank": 13, "team_id": 4}, {"round": 8, "position": "FWD", "avg": 60.5733, "rank": 7, "team_id": 4}, {"round": 8, "position": "MID", "avg": 80.1159, "rank": 13, "team_id": 4}, {"round": 8, "position": "RUC", "avg": 80.7692, "rank": 6, "team_id": 4}]}, "opp3avg": 0, "opp3h": 0, "ven": {"id": 13, "name": "Melbourne Cricket Ground", "display_name": "MCG", "short_name": "MCG", "abbrev": "MCG"}, "venavg": 0, "ven1": {"id": 53, "name": "Perth Stadium", "display_name": "Optus Stadium", "short_name": "Optus", "abbrev": "OS"}, "ven1avg": 0, "ven2": {"id": 7, "name": "Docklands Stadium", "display_name": "Marvel Stadium", "short_name": "Marvel", "abbrev": "MARV"}, "ven2avg": 0, "ven3": {"id": 53, "name": "Perth Stadium", "display_name": "Optus Stadium", "short_name": "Optus", "abbrev": "OS"}, "ven3avg": 0, "trin": 3, "trinp": 0.0142342, "trout": 0, "troutp": 0, "adp": null, "adp_rank": null, "start": 85.7143, "bench": 14.2857, "ownr": 14, "owncr": 3, "owncsr": -15, "livepts": 0, "livegames": 0, "owned": 0.290161, "ppts": 22, "points_per_min": null, "total_points_per_min": null, "mvp_value": null, "position_change": -12, "hot": false, "cold": false, "phot": false, "pcold": false, "position_ranks": [{"pos_rank": "56", "pos_rd_rank": "59", "pos_rank_pos": "RUC"}]}, {"player_id": 240, "round": 9, "points": 0, "price": 123900, "total_points": 0, "position": 577, "games": 0, "total_games": 0, "price_change": 0, "total_price_change": 0, "last_position": 559, "round_position": 415, "minutes_played": 0, "total_minutes_played": 0, "updated_at": "2024-05-12T09:04:26+10:00", "kicks": 0, "total_kicks": 0, "handballs": 0, "total_handballs": 0, "marks": 0, "total_marks": 0, "tackles": 0, "total_tackles": 0, "freekicks_for": 0, "total_freekicks_for": 0, "freekicks_against": 0, "total_freekicks_against": 0, "hitouts": 0, "total_hitouts": 0, "goals": 0, "total_goals": 0, "behinds": 0, "total_behinds": 0, "avg5": 0, "own_raw": 14, "status": "locked", "avg": 0, "std": null, "avg3": 0, "pavg3": 22, "ppts1": 22, "ppts2": 22, "ppts3": 22, "pmin": 22, "pmax": 22, "prange": "22-22", "be1": 23, "be2": 26, "be3": 26, "bp1": null, "bp2": null, "bp3": null, "pp1": 123900, "pp2": 123900, "pp3": 121900, "ppc1": 0, "ppc2": 0, "ppc3": -2000, "ppcs": -7600, "capt": 0, "vice": 0, "own": 0.285122, "ownc": 0.255468, "ownc3": 0.259374, "owncs": 0.2196, "opp": {"id": 14, "abbrev": "SYD", "name": "Sydney", "opposition_ranking": [{"round": 9, "position": "DEF", "avg": 72.7432, "rank": 10, "team_id": 14}, {"round": 9, "position": "FWD", "avg": 54.1413, "rank": 1, "team_id": 14}, {"round": 9, "position": "MID", "avg": 75.3108, "rank": 6, "team_id": 14}, {"round": 9, "position": "RUC", "avg": 77.8462, "rank": 4, "team_id": 14}]}, "oppavg": 0, "opph": 0, "opp1": {"id": 13, "abbrev": "STK", "name": "St Kilda", "opposition_ranking": [{"round": 9, "position": "DEF", "avg": 76.7763, "rank": 15, "team_id": 13}, {"round": 9, "position": "FWD", "avg": 62.7471, "rank": 14, "team_id": 13}, {"round": 9, "position": "MID", "avg": 76.6795, "rank": 9, "team_id": 13}, {"round": 9, "position": "RUC", "avg": 91.9231, "rank": 13, "team_id": 13}]}, "opp1avg": 0, "opp1h": 1, "opp2": {"id": 4, "abbrev": "COL", "name": "Collingwood", "opposition_ranking": [{"round": 9, "position": "DEF", "avg": 75.8493, "rank": 14, "team_id": 4}, {"round": 9, "position": "FWD", "avg": 58.4941, "rank": 3, "team_id": 4}, {"round": 9, "position": "MID", "avg": 77.1429, "rank": 10, "team_id": 4}, {"round": 9, "position": "RUC", "avg": 80.5714, "rank": 7, "team_id": 4}]}, "opp2avg": 0, "opp2h": 0, "opp3": {"id": 10, "abbrev": "MEL", "name": "Melbourne", "opposition_ranking": [{"round": 9, "position": "DEF", "avg": 74.5658, "rank": 13, "team_id": 10}, {"round": 9, "position": "FWD", "avg": 60.7059, "rank": 9, "team_id": 10}, {"round": 9, "position": "MID", "avg": 80.76, "rank": 14, "team_id": 10}, {"round": 9, "position": "RUC", "avg": 80.5714, "rank": 6, "team_id": 10}]}, "opp3avg": 0, "opp3h": 1, "ven": {"id": 53, "name": "Perth Stadium", "display_name": "Optus Stadium", "short_name": "Optus", "abbrev": "OS"}, "venavg": 0, "ven1": {"id": 7, "name": "Docklands Stadium", "display_name": "Marvel Stadium", "short_name": "Marvel", "abbrev": "MARV"}, "ven1avg": 0, "ven2": {"id": 53, "name": "Perth Stadium", "display_name": "Optus Stadium", "short_name": "Optus", "abbrev": "OS"}, "ven2avg": 0, "ven3": {"id": 52, "name": "Traeger Park", "display_name": "TIO Traeger Park", "short_name": "TIO Traeger", "abbrev": "TP"}, "ven3avg": 0, "trin": 0, "trinp": 0, "trout": 3, "troutp": 0.0139444, "adp": null, "adp_rank": null, "start": 81.8182, "bench": 18.1818, "ownr": 11, "owncr": -3, "owncsr": -18, "livepts": 0, "livegames": 0, "owned": 0.366492, "ppts": 22, "points_per_min": null, "total_points_per_min": null, "mvp_value": null, "position_change": -18, "hot": false, "cold": false, "phot": false, "pcold": false, "position_ranks": [{"pos_rank": "56", "pos_rd_rank": "59", "pos_rank_pos": "RUC"}]}, {"player_id": 240, "round": 10, "points": 0, "price": 123900, "total_points": 0, "position": 587, "games": 0, "total_games": 0, "price_change": 0, "total_price_change": 0, "last_position": 577, "round_position": 415, "minutes_played": 0, "total_minutes_played": 0, "updated_at": "2024-05-19T11:37:39+10:00", "kicks": 0, "total_kicks": 0, "handballs": 0, "total_handballs": 0, "marks": 0, "total_marks": 0, "tackles": 0, "total_tackles": 0, "freekicks_for": 0, "total_freekicks_for": 0, "freekicks_against": 0, "total_freekicks_against": 0, "hitouts": 0, "total_hitouts": 0, "goals": 0, "total_goals": 0, "behinds": 0, "total_behinds": 0, "avg5": 0, "own_raw": 11, "status": "locked", "avg": 0, "std": null, "avg3": 0, "pavg3": 14.6667, "ppts1": 22, "ppts2": 22, "ppts3": 0, "pmin": 22, "pmax": 22, "prange": "22-22", "be1": 24, "be2": 28, "be3": 28, "bp1": null, "bp2": null, "bp3": null, "pp1": 123900, "pp2": 123900, "pp3": 123900, "ppc1": 0, "ppc2": 0, "ppc3": 0, "ppcs": -9300, "capt": 0, "vice": 0, "own": 0.282995, "ownc": 0.259823, "ownc3": 0.259551, "owncs": 0.217473, "opp": {"id": 13, "abbrev": "STK", "name": "St Kilda", "opposition_ranking": [{"round": 10, "position": "DEF", "avg": 77.1786, "rank": 16, "team_id": 13}, {"round": 10, "position": "FWD", "avg": 62.732, "rank": 12, "team_id": 13}, {"round": 10, "position": "MID", "avg": 78.2442, "rank": 11, "team_id": 13}, {"round": 10, "position": "RUC", "avg": 96.3571, "rank": 14, "team_id": 13}]}, "oppavg": 0, "opph": 1, "opp1": {"id": 4, "abbrev": "COL", "name": "Collingwood", "opposition_ranking": [{"round": 10, "position": "DEF", "avg": 75.9259, "rank": 15, "team_id": 4}, {"round": 10, "position": "FWD", "avg": 58.9149, "rank": 4, "team_id": 4}, {"round": 10, "position": "MID", "avg": 77.2706, "rank": 8, "team_id": 4}, {"round": 10, "position": "RUC", "avg": 84, "rank": 8, "team_id": 4}]}, "opp1avg": 0, "opp1h": 0, "opp2": {"id": 10, "abbrev": "MEL", "name": "Melbourne", "opposition_ranking": [{"round": 10, "position": "DEF", "avg": 74.8353, "rank": 13, "team_id": 10}, {"round": 10, "position": "FWD", "avg": 62.3723, "rank": 11, "team_id": 10}, {"round": 10, "position": "MID", "avg": 80.9512, "rank": 14, "team_id": 10}, {"round": 10, "position": "RUC", "avg": 79, "rank": 5, "team_id": 10}]}, "opp2avg": 0, "opp2h": 1, "opp3": null, "opp3avg": 0, "opp3h": null, "ven": {"id": 7, "name": "Docklands Stadium", "display_name": "Marvel Stadium", "short_name": "Marvel", "abbrev": "MARV"}, "venavg": 0, "ven1": {"id": 53, "name": "Perth Stadium", "display_name": "Optus Stadium", "short_name": "Optus", "abbrev": "OS"}, "ven1avg": 0, "ven2": {"id": 52, "name": "Traeger Park", "display_name": "TIO Traeger Park", "short_name": "TIO Traeger", "abbrev": "TP"}, "ven2avg": 0, "ven3": null, "ven3avg": 0, "trin": 1, "trinp": 0.00538706, "trout": 1, "troutp": 0.00538706, "adp": null, "adp_rank": null, "start": 72.7273, "bench": 27.2727, "ownr": 11, "owncr": 0, "owncsr": -18, "livepts": 0, "livegames": 0, "owned": 0.285122, "ppts": 22, "points_per_min": null, "total_points_per_min": null, "mvp_value": null, "position_change": -10, "hot": false, "cold": false, "phot": false, "pcold": false, "position_ranks": [{"pos_rank": "58", "pos_rd_rank": "59", "pos_rank_pos": "RUC"}]}, {"player_id": 240, "round": 11, "points": 0, "price": 123900, "total_points": 0, "position": 597, "games": 0, "total_games": 0, "price_change": 0, "total_price_change": 0, "last_position": 587, "round_position": 411, "minutes_played": 0, "total_minutes_played": 0, "updated_at": "2024-05-26T09:38:44+10:00", "kicks": 0, "total_kicks": 0, "handballs": 0, "total_handballs": 0, "marks": 0, "total_marks": 0, "tackles": 0, "total_tackles": 0, "freekicks_for": 0, "total_freekicks_for": 0, "freekicks_against": 0, "total_freekicks_against": 0, "hitouts": 0, "total_hitouts": 0, "goals": 0, "total_goals": 0, "behinds": 0, "total_behinds": 0, "avg5": 0, "own_raw": 11, "status": "locked", "avg": 0, "std": null, "avg3": 0, "pavg3": 14.6667, "ppts1": 22, "ppts2": 0, "ppts3": 22, "pmin": 22, "pmax": 22, "prange": "22-22", "be1": 24, "be2": 28, "be3": 28, "bp1": null, "bp2": null, "bp3": null, "pp1": 123900, "pp2": 123900, "pp3": 123900, "ppc1": 0, "ppc2": 0, "ppc3": 0, "ppcs": -10000, "capt": 0, "vice": 0, "own": 0.281402, "ownc": 0.258328, "ownc3": 0.251748, "owncs": 0.21588, "opp": {"id": 4, "abbrev": "COL", "name": "Collingwood", "opposition_ranking": [{"round": 11, "position": "DEF", "avg": 76.9889, "rank": 16, "team_id": 4}, {"round": 11, "position": "FWD", "avg": 58.4412, "rank": 3, "team_id": 4}, {"round": 11, "position": "MID", "avg": 77.4946, "rank": 10, "team_id": 4}, {"round": 11, "position": "RUC", "avg": 84.7059, "rank": 8, "team_id": 4}]}, "oppavg": 0, "opph": 0, "opp1": {"id": 10, "abbrev": "MEL", "name": "Melbourne", "opposition_ranking": [{"round": 11, "position": "DEF", "avg": 74.0532, "rank": 12, "team_id": 10}, {"round": 11, "position": "FWD", "avg": 61.4216, "rank": 11, "team_id": 10}, {"round": 11, "position": "MID", "avg": 80.4505, "rank": 15, "team_id": 10}, {"round": 11, "position": "RUC", "avg": 78.625, "rank": 5, "team_id": 10}]}, "opp1avg": 0, "opp1h": 1, "opp2": null, "opp2avg": 0, "opp2h": null, "opp3": {"id": 15, "abbrev": "WBD", "name": "Western Bulldogs", "opposition_ranking": [{"round": 11, "position": "DEF", "avg": 71.2421, "rank": 7, "team_id": 15}, {"round": 11, "position": "FWD", "avg": 59.5182, "rank": 5, "team_id": 15}, {"round": 11, "position": "MID", "avg": 73.2935, "rank": 3, "team_id": 15}, {"round": 11, "position": "RUC", "avg": 86.6875, "rank": 10, "team_id": 15}]}, "opp3avg": 0, "opp3h": 1, "ven": {"id": 53, "name": "Perth Stadium", "display_name": "Optus Stadium", "short_name": "Optus", "abbrev": "OS"}, "venavg": 0, "ven1": {"id": 52, "name": "Traeger Park", "display_name": "TIO Traeger Park", "short_name": "TIO Traeger", "abbrev": "TP"}, "ven1avg": 0, "ven2": null, "ven2avg": 0, "ven3": {"id": 7, "name": "Docklands Stadium", "display_name": "Marvel Stadium", "short_name": "Marvel", "abbrev": "MARV"}, "ven3avg": 0, "trin": 0, "trinp": 0, "trout": 0, "troutp": 0, "adp": null, "adp_rank": null, "start": 72.7273, "bench": 27.2727, "ownr": 11, "owncr": 0, "owncsr": -18, "livepts": 0, "livegames": 0, "owned": 0.282995, "ppts": 22, "points_per_min": null, "total_points_per_min": null, "mvp_value": null, "position_change": -10, "hot": false, "cold": false, "phot": false, "pcold": false, "position_ranks": [{"pos_rank": "58", "pos_rd_rank": "59", "pos_rank_pos": "RUC"}]}, {"player_id": 240, "round": 12, "points": 0, "price": 123900, "total_points": 0, "position": 602, "games": 0, "total_games": 0, "price_change": 0, "total_price_change": 0, "last_position": 597, "round_position": 323, "minutes_played": 0, "total_minutes_played": 0, "updated_at": "2024-06-02T10:27:49+10:00", "kicks": 0, "total_kicks": 0, "handballs": 0, "total_handballs": 0, "marks": 0, "total_marks": 0, "tackles": 0, "total_tackles": 0, "freekicks_for": 0, "total_freekicks_for": 0, "freekicks_against": 0, "total_freekicks_against": 0, "hitouts": 0, "total_hitouts": 0, "goals": 0, "total_goals": 0, "behinds": 0, "total_behinds": 0, "avg5": 0, "own_raw": 11, "status": "locked", "avg": 0, "std": null, "avg3": 0, "pavg3": 14.6667, "ppts1": 0, "ppts2": 22, "ppts3": 22, "pmin": 0, "pmax": 0, "prange": "0-0", "be1": 24, "be2": 24, "be3": 28, "bp1": null, "bp2": null, "bp3": null, "pp1": 123900, "pp2": 123900, "pp3": 123900, "ppc1": 0, "ppc2": 0, "ppc3": 0, "ppcs": -9000, "capt": 0, "vice": 0, "own": 0.228949, "ownc": 0.205992, "ownc3": 0.205778, "owncs": 0.163427, "opp": {"id": 10, "abbrev": "MEL", "name": "Melbourne", "opposition_ranking": [{"round": 12, "position": "DEF", "avg": 74.4563, "rank": 11, "team_id": 10}, {"round": 12, "position": "FWD", "avg": 63.4071, "rank": 14, "team_id": 10}, {"round": 12, "position": "MID", "avg": 80.4314, "rank": 15, "team_id": 10}, {"round": 12, "position": "RUC", "avg": 79.7895, "rank": 5, "team_id": 10}]}, "oppavg": 0, "opph": 1, "opp1": null, "opp1avg": 0, "opp1h": null, "opp2": {"id": 15, "abbrev": "WBD", "name": "Western Bulldogs", "opposition_ranking": [{"round": 12, "position": "DEF", "avg": 71.5, "rank": 7, "team_id": 15}, {"round": 12, "position": "FWD", "avg": 59.359, "rank": 5, "team_id": 15}, {"round": 12, "position": "MID", "avg": 73.2524, "rank": 3, "team_id": 15}, {"round": 12, "position": "RUC", "avg": 84.4444, "rank": 7, "team_id": 15}]}, "opp2avg": 0, "opp2h": 1, "opp3": {"id": 17, "abbrev": "GCS", "name": "Gold Coast", "opposition_ranking": [{"round": 12, "position": "DEF", "avg": 74.6635, "rank": 13, "team_id": 17}, {"round": 12, "position": "FWD", "avg": 60.6636, "rank": 7, "team_id": 17}, {"round": 12, "position": "MID", "avg": 72.6355, "rank": 1, "team_id": 17}, {"round": 12, "position": "RUC", "avg": 81.75, "rank": 6, "team_id": 17}]}, "opp3avg": 0, "opp3h": 0, "ven": {"id": 52, "name": "Traeger Park", "display_name": "TIO Traeger Park", "short_name": "TIO Traeger", "abbrev": "TP"}, "venavg": 0, "ven1": null, "ven1avg": 0, "ven2": {"id": 7, "name": "Docklands Stadium", "display_name": "Marvel Stadium", "short_name": "Marvel", "abbrev": "MARV"}, "ven2avg": 0, "ven3": {"id": 53, "name": "Perth Stadium", "display_name": "Optus Stadium", "short_name": "Optus", "abbrev": "OS"}, "ven3avg": 0, "trin": 0, "trinp": 0, "trout": 2, "troutp": 0.0104668, "adp": null, "adp_rank": null, "start": 66.6667, "bench": 33.3333, "ownr": 9, "owncr": -2, "owncsr": -20, "livepts": 0, "livegames": 0, "owned": 0.281402, "ppts": 22, "points_per_min": null, "total_points_per_min": null, "mvp_value": null, "position_change": -5, "hot": false, "cold": false, "phot": false, "pcold": false, "position_ranks": [{"pos_rank": "63", "pos_rd_rank": "61", "pos_rank_pos": "RUC"}]}, {"player_id": 240, "round": 13, "points": 0, "price": 123900, "total_points": 0, "position": 607, "games": 0, "total_games": 0, "price_change": 0, "total_price_change": 0, "last_position": 602, "round_position": 368, "minutes_played": 0, "total_minutes_played": 0, "updated_at": "2024-06-10T08:19:51+10:00", "kicks": 0, "total_kicks": 0, "handballs": 0, "total_handballs": 0, "marks": 0, "total_marks": 0, "tackles": 0, "total_tackles": 0, "freekicks_for": 0, "total_freekicks_for": 0, "freekicks_against": 0, "total_freekicks_against": 0, "hitouts": 0, "total_hitouts": 0, "goals": 0, "total_goals": 0, "behinds": 0, "total_behinds": 0, "avg5": 0, "own_raw": 9, "status": "locked", "avg": 0, "std": null, "avg3": 0, "pavg3": 22, "ppts1": 22, "ppts2": 22, "ppts3": 22, "pmin": 22, "pmax": 22, "prange": "22-22", "be1": 24, "be2": 29, "be3": 29, "bp1": null, "bp2": null, "bp3": null, "pp1": 123900, "pp2": 123900, "pp3": 120900, "ppc1": 0, "ppc2": 0, "ppc3": -3000, "ppcs": -10600, "capt": 0, "vice": 0, "own": 0.228137, "ownc": 0.209418, "ownc3": 0.205063, "owncs": 0.162615, "opp": null, "oppavg": null, "opph": null, "opp1": {"id": 15, "abbrev": "WBD", "name": "Western Bulldogs", "opposition_ranking": [{"round": 13, "position": "DEF", "avg": 70.7876, "rank": 7, "team_id": 15}, {"round": 13, "position": "FWD", "avg": 60.4922, "rank": 8, "team_id": 15}, {"round": 13, "position": "MID", "avg": 74.2566, "rank": 4, "team_id": 15}, {"round": 13, "position": "RUC", "avg": 86.8947, "rank": 10, "team_id": 15}]}, "opp1avg": 0, "opp1h": 1, "opp2": {"id": 17, "abbrev": "GCS", "name": "Gold Coast", "opposition_ranking": [{"round": 13, "position": "DEF", "avg": 74.5982, "rank": 11, "team_id": 17}, {"round": 13, "position": "FWD", "avg": 60.4068, "rank": 7, "team_id": 17}, {"round": 13, "position": "MID", "avg": 72.4153, "rank": 1, "team_id": 17}, {"round": 13, "position": "RUC", "avg": 83.8235, "rank": 7, "team_id": 17}]}, "opp2avg": 0, "opp2h": 0, "opp3": {"id": 14, "abbrev": "SYD", "name": "Sydney", "opposition_ranking": [{"round": 13, "position": "DEF", "avg": 72.83, "rank": 10, "team_id": 14}, {"round": 13, "position": "FWD", "avg": 55.3, "rank": 1, "team_id": 14}, {"round": 13, "position": "MID", "avg": 73.4369, "rank": 3, "team_id": 14}, {"round": 13, "position": "RUC", "avg": 72.2105, "rank": 1, "team_id": 14}]}, "opp3avg": 0, "opp3h": 1, "ven": null, "venavg": 0, "ven1": {"id": 7, "name": "Docklands Stadium", "display_name": "Marvel Stadium", "short_name": "Marvel", "abbrev": "MARV"}, "ven1avg": 0, "ven2": {"id": 53, "name": "Perth Stadium", "display_name": "Optus Stadium", "short_name": "Optus", "abbrev": "OS"}, "ven2avg": 0, "ven3": {"id": 16, "name": "Sydney Cricket Ground", "display_name": "SCG", "short_name": "SCG", "abbrev": "SCG"}, "ven3avg": 0, "trin": 1, "trinp": 0.00405943, "trout": 1, "troutp": 0.00405943, "adp": null, "adp_rank": null, "start": 77.7778, "bench": 22.2222, "ownr": 9, "owncr": 0, "owncsr": -20, "livepts": 0, "livegames": 0, "owned": 0.228949, "ppts": 0, "points_per_min": null, "total_points_per_min": null, "mvp_value": null, "position_change": -5, "hot": false, "cold": false, "phot": false, "pcold": false, "position_ranks": [{"pos_rank": "62", "pos_rd_rank": "61", "pos_rank_pos": "RUC"}]}, {"player_id": 240, "round": 14, "points": 0, "price": 123900, "total_points": 0, "position": 614, "games": 0, "total_games": 0, "price_change": 0, "total_price_change": 0, "last_position": 607, "round_position": 277, "minutes_played": 0, "total_minutes_played": 0, "updated_at": "2024-06-16T09:24:52+10:00", "kicks": 0, "total_kicks": 0, "handballs": 0, "total_handballs": 0, "marks": 0, "total_marks": 0, "tackles": 0, "total_tackles": 0, "freekicks_for": 0, "total_freekicks_for": 0, "freekicks_against": 0, "total_freekicks_against": 0, "hitouts": 0, "total_hitouts": 0, "goals": 0, "total_goals": 0, "behinds": 0, "total_behinds": 0, "avg5": 0, "own_raw": 9, "status": "locked", "avg": 0, "std": null, "avg3": 0, "pavg3": 22, "ppts1": 22, "ppts2": 22, "ppts3": 22, "pmin": 22, "pmax": 22, "prange": "22-22", "be1": 24, "be2": 28, "be3": 28, "bp1": null, "bp2": null, "bp3": null, "pp1": 123900, "pp2": 123900, "pp3": 121100, "ppc1": 0, "ppc2": 0, "ppc3": -2800, "ppcs": -9900, "capt": 0, "vice": 0, "own": 0.227043, "ownc": 0.208376, "ownc3": 0.204086, "owncs": 0.161521, "opp": {"id": 15, "abbrev": "WBD", "name": "Western Bulldogs", "opposition_ranking": [{"round": 14, "position": "DEF", "avg": 70.3554, "rank": 4, "team_id": 15}, {"round": 14, "position": "FWD", "avg": 60.2263, "rank": 6, "team_id": 15}, {"round": 14, "position": "MID", "avg": 72.9091, "rank": 3, "team_id": 15}, {"round": 14, "position": "RUC", "avg": 88.7619, "rank": 11, "team_id": 15}]}, "oppavg": 0, "opph": 1, "opp1": {"id": 17, "abbrev": "GCS", "name": "Gold Coast", "opposition_ranking": [{"round": 14, "position": "DEF", "avg": 74.5982, "rank": 12, "team_id": 17}, {"round": 14, "position": "FWD", "avg": 60.4068, "rank": 8, "team_id": 17}, {"round": 14, "position": "MID", "avg": 72.4153, "rank": 2, "team_id": 17}, {"round": 14, "position": "RUC", "avg": 83.8235, "rank": 8, "team_id": 17}]}, "opp1avg": 0, "opp1h": 0, "opp2": {"id": 14, "abbrev": "SYD", "name": "Sydney", "opposition_ranking": [{"round": 14, "position": "DEF", "avg": 72.4128, "rank": 9, "team_id": 14}, {"round": 14, "position": "FWD", "avg": 55.7244, "rank": 1, "team_id": 14}, {"round": 14, "position": "MID", "avg": 73.0089, "rank": 4, "team_id": 14}, {"round": 14, "position": "RUC", "avg": 72.2, "rank": 1, "team_id": 14}]}, "opp2avg": 0, "opp2h": 1, "opp3": {"id": 12, "abbrev": "RIC", "name": "Richmond", "opposition_ranking": [{"round": 14, "position": "DEF", "avg": 79.9032, "rank": 18, "team_id": 12}, {"round": 14, "position": "FWD", "avg": 67.442, "rank": 17, "team_id": 12}, {"round": 14, "position": "MID", "avg": 88.2328, "rank": 18, "team_id": 12}, {"round": 14, "position": "RUC", "avg": 91.1765, "rank": 14, "team_id": 12}]}, "opp3avg": 0, "opp3h": 0, "ven": {"id": 7, "name": "Docklands Stadium", "display_name": "Marvel Stadium", "short_name": "Marvel", "abbrev": "MARV"}, "venavg": 0, "ven1": {"id": 53, "name": "Perth Stadium", "display_name": "Optus Stadium", "short_name": "Optus", "abbrev": "OS"}, "ven1avg": 0, "ven2": {"id": 16, "name": "Sydney Cricket Ground", "display_name": "SCG", "short_name": "SCG", "abbrev": "SCG"}, "ven2avg": 0, "ven3": {"id": 53, "name": "Perth Stadium", "display_name": "Optus Stadium", "short_name": "Optus", "abbrev": "OS"}, "ven3avg": 0, "trin": 0, "trinp": 0, "trout": 0, "troutp": 0, "adp": null, "adp_rank": null, "start": 77.7778, "bench": 22.2222, "ownr": 9, "owncr": 0, "owncsr": -20, "livepts": 0, "livegames": 0, "owned": 0.228137, "ppts": 22, "points_per_min": null, "total_points_per_min": null, "mvp_value": null, "position_change": -7, "hot": false, "cold": false, "phot": false, "pcold": false, "position_ranks": [{"pos_rank": "62", "pos_rd_rank": "55", "pos_rank_pos": "RUC"}]}, {"player_id": 240, "round": 15, "points": 0, "price": 123900, "total_points": 0, "position": 619, "games": 0, "total_games": 0, "price_change": 0, "total_price_change": 0, "last_position": 614, "round_position": 277, "minutes_played": 0, "total_minutes_played": 0, "updated_at": "2024-06-23T08:49:10+10:00", "kicks": 0, "total_kicks": 0, "handballs": 0, "total_handballs": 0, "marks": 0, "total_marks": 0, "tackles": 0, "total_tackles": 0, "freekicks_for": 0, "total_freekicks_for": 0, "freekicks_against": 0, "total_freekicks_against": 0, "hitouts": 0, "total_hitouts": 0, "goals": 0, "total_goals": 0, "behinds": 0, "total_behinds": 0, "avg5": 0, "own_raw": 9, "status": "locked", "avg": 0, "std": null, "avg3": 0, "pavg3": 22, "ppts1": 22, "ppts2": 22, "ppts3": 22, "pmin": 22, "pmax": 22, "prange": "22-22", "be1": 24, "be2": 28, "be3": 28, "bp1": null, "bp2": null, "bp3": null, "pp1": 123900, "pp2": 123900, "pp3": 121200, "ppc1": 0, "ppc2": 0, "ppc3": -2700, "ppcs": -8900, "capt": 0, "vice": 0, "own": 0.226244, "ownc": 0.207642, "ownc3": 0.207526, "owncs": 0.160722, "opp": {"id": 17, "abbrev": "GCS", "name": "Gold Coast", "opposition_ranking": [{"round": 15, "position": "DEF", "avg": 74.0331, "rank": 11, "team_id": 17}, {"round": 15, "position": "FWD", "avg": 60.4524, "rank": 8, "team_id": 17}, {"round": 15, "position": "MID", "avg": 73.4921, "rank": 4, "team_id": 17}, {"round": 15, "position": "RUC", "avg": 86.2105, "rank": 8, "team_id": 17}]}, "oppavg": 0, "opph": 0, "opp1": {"id": 14, "abbrev": "SYD", "name": "Sydney", "opposition_ranking": [{"round": 15, "position": "DEF", "avg": 73.1565, "rank": 10, "team_id": 14}, {"round": 15, "position": "FWD", "avg": 55.7536, "rank": 1, "team_id": 14}, {"round": 15, "position": "MID", "avg": 73.1901, "rank": 3, "team_id": 14}, {"round": 15, "position": "RUC", "avg": 71, "rank": 1, "team_id": 14}]}, "opp1avg": 0, "opp1h": 1, "opp2": {"id": 12, "abbrev": "RIC", "name": "Richmond", "opposition_ranking": [{"round": 15, "position": "DEF", "avg": 79.9032, "rank": 18, "team_id": 12}, {"round": 15, "position": "FWD", "avg": 67.442, "rank": 17, "team_id": 12}, {"round": 15, "position": "MID", "avg": 88.2328, "rank": 18, "team_id": 12}, {"round": 15, "position": "RUC", "avg": 91.1765, "rank": 14, "team_id": 12}]}, "opp2avg": 0, "opp2h": 0, "opp3": {"id": 8, "abbrev": "HAW", "name": "Hawthorn", "opposition_ranking": [{"round": 15, "position": "DEF", "avg": 72.4274, "rank": 9, "team_id": 8}, {"round": 15, "position": "FWD", "avg": 62.5942, "rank": 10, "team_id": 8}, {"round": 15, "position": "MID", "avg": 78.8915, "rank": 13, "team_id": 8}, {"round": 15, "position": "RUC", "avg": 101.789, "rank": 17, "team_id": 8}]}, "opp3avg": 0, "opp3h": 1, "ven": {"id": 53, "name": "Perth Stadium", "display_name": "Optus Stadium", "short_name": "Optus", "abbrev": "OS"}, "venavg": 0, "ven1": {"id": 16, "name": "Sydney Cricket Ground", "display_name": "SCG", "short_name": "SCG", "abbrev": "SCG"}, "ven1avg": 0, "ven2": {"id": 53, "name": "Perth Stadium", "display_name": "Optus Stadium", "short_name": "Optus", "abbrev": "OS"}, "ven2avg": 0, "ven3": {"id": 54, "name": "University of Tasmania Stadium", "display_name": "University of Tasmania Stadium", "short_name": "UoT", "abbrev": "UTS"}, "ven3avg": 0, "trin": 0, "trinp": 0, "trout": 0, "troutp": 0, "adp": null, "adp_rank": null, "start": 77.7778, "bench": 22.2222, "ownr": 9, "owncr": 0, "owncsr": -20, "livepts": 0, "livegames": 0, "owned": 0.227043, "ppts": 22, "points_per_min": null, "total_points_per_min": null, "mvp_value": null, "position_change": -5, "hot": false, "cold": false, "phot": false, "pcold": false, "position_ranks": [{"pos_rank": "65", "pos_rd_rank": "61", "pos_rank_pos": "RUC"}]}, {"player_id": 240, "round": 16, "points": 0, "price": 123900, "total_points": 0, "position": 628, "games": 0, "total_games": 0, "price_change": 0, "total_price_change": 0, "last_position": 619, "round_position": 415, "minutes_played": 0, "total_minutes_played": 0, "updated_at": "2024-06-30T09:29:07+10:00", "kicks": 0, "total_kicks": 0, "handballs": 0, "total_handballs": 0, "marks": 0, "total_marks": 0, "tackles": 0, "total_tackles": 0, "freekicks_for": 0, "total_freekicks_for": 0, "freekicks_against": 0, "total_freekicks_against": 0, "hitouts": 0, "total_hitouts": 0, "goals": 0, "total_goals": 0, "behinds": 0, "total_behinds": 0, "avg5": 0, "own_raw": 9, "status": "locked", "avg": 0, "std": null, "avg3": 0, "pavg3": 22, "ppts1": 22, "ppts2": 22, "ppts3": 22, "pmin": 22, "pmax": 22, "prange": "22-22", "be1": 24, "be2": 27, "be3": 27, "bp1": null, "bp2": null, "bp3": null, "pp1": 123900, "pp2": 123900, "pp3": 121700, "ppc1": 0, "ppc2": 0, "ppc3": -2200, "ppcs": -7300, "capt": 0, "vice": 0, "own": 0.22579, "ownc": 0.207229, "ownc3": 0.207123, "owncs": 0.160268, "opp": {"id": 14, "abbrev": "SYD", "name": "Sydney", "opposition_ranking": [{"round": 16, "position": "DEF", "avg": 72.75, "rank": 9, "team_id": 14}, {"round": 16, "position": "FWD", "avg": 56.6096, "rank": 1, "team_id": 14}, {"round": 16, "position": "MID", "avg": 73.0388, "rank": 3, "team_id": 14}, {"round": 16, "position": "RUC", "avg": 71.4783, "rank": 1, "team_id": 14}]}, "oppavg": 0, "opph": 1, "opp1": {"id": 12, "abbrev": "RIC", "name": "Richmond", "opposition_ranking": [{"round": 16, "position": "DEF", "avg": 79.9474, "rank": 18, "team_id": 12}, {"round": 16, "position": "FWD", "avg": 67.869, "rank": 17, "team_id": 12}, {"round": 16, "position": "MID", "avg": 88.5161, "rank": 18, "team_id": 12}, {"round": 16, "position": "RUC", "avg": 89.2778, "rank": 11, "team_id": 12}]}, "opp1avg": 0, "opp1h": 0, "opp2": {"id": 8, "abbrev": "HAW", "name": "Hawthorn", "opposition_ranking": [{"round": 16, "position": "DEF", "avg": 72.7717, "rank": 10, "team_id": 8}, {"round": 16, "position": "FWD", "avg": 61.3356, "rank": 10, "team_id": 8}, {"round": 16, "position": "MID", "avg": 78.1111, "rank": 10, "team_id": 8}, {"round": 16, "position": "RUC", "avg": 96.381, "rank": 16, "team_id": 8}]}, "opp2avg": 0, "opp2h": 1, "opp3": {"id": 10, "abbrev": "MEL", "name": "Melbourne", "opposition_ranking": [{"round": 16, "position": "DEF", "avg": 75.1094, "rank": 15, "team_id": 10}, {"round": 16, "position": "FWD", "avg": 65.1655, "rank": 14, "team_id": 10}, {"round": 16, "position": "MID", "avg": 80.4394, "rank": 15, "team_id": 10}, {"round": 16, "position": "RUC", "avg": 80.0417, "rank": 5, "team_id": 10}]}, "opp3avg": 0, "opp3h": 0, "ven": {"id": 16, "name": "Sydney Cricket Ground", "display_name": "SCG", "short_name": "SCG", "abbrev": "SCG"}, "venavg": 0, "ven1": {"id": 53, "name": "Perth Stadium", "display_name": "Optus Stadium", "short_name": "Optus", "abbrev": "OS"}, "ven1avg": 0, "ven2": {"id": 54, "name": "University of Tasmania Stadium", "display_name": "University of Tasmania Stadium", "short_name": "UoT", "abbrev": "UTS"}, "ven2avg": 0, "ven3": {"id": 53, "name": "Perth Stadium", "display_name": "Optus Stadium", "short_name": "Optus", "abbrev": "OS"}, "ven3avg": 0, "trin": 1, "trinp": 0.00655953, "trout": 1, "troutp": 0.00655953, "adp": null, "adp_rank": null, "start": 77.7778, "bench": 22.2222, "ownr": 9, "owncr": 0, "owncsr": -20, "livepts": 0, "livegames": 0, "owned": 0.226244, "ppts": 22, "points_per_min": null, "total_points_per_min": null, "mvp_value": null, "position_change": -9, "hot": false, "cold": false, "phot": false, "pcold": false, "position_ranks": [{"pos_rank": "69", "pos_rd_rank": "61", "pos_rank_pos": "RUC"}]}, {"player_id": 240, "round": 17, "points": 0, "price": 123900, "total_points": 0, "position": 631, "games": 0, "total_games": 0, "price_change": 0, "total_price_change": 0, "last_position": 628, "round_position": 414, "minutes_played": 0, "total_minutes_played": 0, "updated_at": "2024-07-07T09:18:23+10:00", "kicks": 0, "total_kicks": 0, "handballs": 0, "total_handballs": 0, "marks": 0, "total_marks": 0, "tackles": 0, "total_tackles": 0, "freekicks_for": 0, "total_freekicks_for": 0, "freekicks_against": 0, "total_freekicks_against": 0, "hitouts": 0, "total_hitouts": 0, "goals": 0, "total_goals": 0, "behinds": 0, "total_behinds": 0, "avg5": 0, "own_raw": 9, "status": "locked", "avg": 0, "std": null, "avg3": 0, "pavg3": 22, "ppts1": 22, "ppts2": 22, "ppts3": 22, "pmin": 22, "pmax": 22, "prange": "22-22", "be1": 24, "be2": 27, "be3": 27, "bp1": null, "bp2": null, "bp3": null, "pp1": 123900, "pp2": 123900, "pp3": 121500, "ppc1": 0, "ppc2": 0, "ppc3": -2400, "ppcs": -7200, "capt": 0, "vice": 0, "own": 0.225564, "ownc": 0.207029, "ownc3": 0.206962, "owncs": 0.160042, "opp": {"id": 12, "abbrev": "RIC", "name": "Richmond", "opposition_ranking": [{"round": 17, "position": "DEF", "avg": 80.1915, "rank": 18, "team_id": 12}, {"round": 17, "position": "FWD", "avg": 67.9935, "rank": 17, "team_id": 12}, {"round": 17, "position": "MID", "avg": 87.9242, "rank": 18, "team_id": 12}, {"round": 17, "position": "RUC", "avg": 88.95, "rank": 11, "team_id": 12}]}, "oppavg": 0, "opph": 0, "opp1": {"id": 8, "abbrev": "HAW", "name": "Hawthorn", "opposition_ranking": [{"round": 17, "position": "DEF", "avg": 73.9051, "rank": 11, "team_id": 8}, {"round": 17, "position": "FWD", "avg": 62.2774, "rank": 12, "team_id": 8}, {"round": 17, "position": "MID", "avg": 78.1103, "rank": 10, "team_id": 8}, {"round": 17, "position": "RUC", "avg": 96.5909, "rank": 16, "team_id": 8}]}, "opp1avg": 0, "opp1h": 1, "opp2": {"id": 10, "abbrev": "MEL", "name": "Melbourne", "opposition_ranking": [{"round": 17, "position": "DEF", "avg": 74.5145, "rank": 14, "team_id": 10}, {"round": 17, "position": "FWD", "avg": 64.6216, "rank": 14, "team_id": 10}, {"round": 17, "position": "MID", "avg": 79.9783, "rank": 15, "team_id": 10}, {"round": 17, "position": "RUC", "avg": 76.8846, "rank": 2, "team_id": 10}]}, "opp2avg": 0, "opp2h": 0, "opp3": {"id": 16, "abbrev": "WCE", "name": "West Coast", "opposition_ranking": [{"round": 17, "position": "DEF", "avg": 76.5652, "rank": 16, "team_id": 16}, {"round": 17, "position": "FWD", "avg": 67.8165, "rank": 16, "team_id": 16}, {"round": 17, "position": "MID", "avg": 84.9577, "rank": 17, "team_id": 16}, {"round": 17, "position": "RUC", "avg": 105.95, "rank": 18, "team_id": 16}]}, "opp3avg": 0, "opp3h": 0, "ven": {"id": 53, "name": "Perth Stadium", "display_name": "Optus Stadium", "short_name": "Optus", "abbrev": "OS"}, "venavg": 0, "ven1": {"id": 54, "name": "University of Tasmania Stadium", "display_name": "University of Tasmania Stadium", "short_name": "UoT", "abbrev": "UTS"}, "ven1avg": 0, "ven2": {"id": 53, "name": "Perth Stadium", "display_name": "Optus Stadium", "short_name": "Optus", "abbrev": "OS"}, "ven2avg": 0, "ven3": {"id": 53, "name": "Perth Stadium", "display_name": "Optus Stadium", "short_name": "Optus", "abbrev": "OS"}, "ven3avg": 0, "trin": 0, "trinp": 0, "trout": 0, "troutp": 0, "adp": null, "adp_rank": null, "start": 77.7778, "bench": 22.2222, "ownr": 9, "owncr": 0, "owncsr": -20, "livepts": 0, "livegames": 0, "owned": 0.22579, "ppts": 22, "points_per_min": null, "total_points_per_min": null, "mvp_value": null, "position_change": -3, "hot": false, "cold": false, "phot": false, "pcold": false, "position_ranks": [{"pos_rank": "69", "pos_rd_rank": "61", "pos_rank_pos": "RUC"}]}, {"player_id": 240, "round": 18, "points": 0, "price": 123900, "total_points": 0, "position": 635, "games": 0, "total_games": 0, "price_change": 0, "total_price_change": 0, "last_position": 631, "round_position": 414, "minutes_played": 0, "total_minutes_played": 0, "updated_at": "2024-07-14T09:46:24+10:00", "kicks": 0, "total_kicks": 0, "handballs": 0, "total_handballs": 0, "marks": 0, "total_marks": 0, "tackles": 0, "total_tackles": 0, "freekicks_for": 0, "total_freekicks_for": 0, "freekicks_against": 0, "total_freekicks_against": 0, "hitouts": 0, "total_hitouts": 0, "goals": 0, "total_goals": 0, "behinds": 0, "total_behinds": 0, "avg5": 0, "own_raw": 9, "status": "locked", "avg": 0, "std": null, "avg3": 0, "pavg3": 22, "ppts1": 22, "ppts2": 22, "ppts3": 22, "pmin": 22, "pmax": 22, "prange": "22-22", "be1": 24, "be2": 28, "be3": 28, "bp1": null, "bp2": null, "bp3": null, "pp1": 123900, "pp2": 123900, "pp3": 121400, "ppc1": 0, "ppc2": 0, "ppc3": -2500, "ppcs": -6800, "capt": 0, "vice": 0, "own": 0.249563, "ownc": 0.231077, "ownc3": 0.231002, "owncs": 0.184041, "opp": {"id": 8, "abbrev": "HAW", "name": "Hawthorn", "opposition_ranking": [{"round": 18, "position": "DEF", "avg": 74.5069, "rank": 12, "team_id": 8}, {"round": 18, "position": "FWD", "avg": 62.1369, "rank": 13, "team_id": 8}, {"round": 18, "position": "MID", "avg": 78.4416, "rank": 11, "team_id": 8}, {"round": 18, "position": "RUC", "avg": 97.4348, "rank": 17, "team_id": 8}]}, "oppavg": 0, "opph": 1, "opp1": {"id": 10, "abbrev": "MEL", "name": "Melbourne", "opposition_ranking": [{"round": 18, "position": "DEF", "avg": 74.5541, "rank": 13, "team_id": 10}, {"round": 18, "position": "FWD", "avg": 63.9091, "rank": 14, "team_id": 10}, {"round": 18, "position": "MID", "avg": 80.0068, "rank": 15, "team_id": 10}, {"round": 18, "position": "RUC", "avg": 77.5185, "rank": 4, "team_id": 10}]}, "opp1avg": 0, "opp1h": 0, "opp2": {"id": 16, "abbrev": "WCE", "name": "West Coast", "opposition_ranking": [{"round": 18, "position": "DEF", "avg": 75.9444, "rank": 16, "team_id": 16}, {"round": 18, "position": "FWD", "avg": 68.0805, "rank": 16, "team_id": 16}, {"round": 18, "position": "MID", "avg": 84.987, "rank": 17, "team_id": 16}, {"round": 18, "position": "RUC", "avg": 106.238, "rank": 18, "team_id": 16}]}, "opp2avg": 0, "opp2h": 0, "opp3": {"id": 5, "abbrev": "ESS", "name": "Essendon", "opposition_ranking": [{"round": 18, "position": "DEF", "avg": 71.3782, "rank": 8, "team_id": 5}, {"round": 18, "position": "FWD", "avg": 59.1243, "rank": 4, "team_id": 5}, {"round": 18, "position": "MID", "avg": 75.6691, "rank": 7, "team_id": 5}, {"round": 18, "position": "RUC", "avg": 77.4348, "rank": 3, "team_id": 5}]}, "opp3avg": 0, "opp3h": 1, "ven": {"id": 54, "name": "University of Tasmania Stadium", "display_name": "University of Tasmania Stadium", "short_name": "UoT", "abbrev": "UTS"}, "venavg": 0, "ven1": {"id": 53, "name": "Perth Stadium", "display_name": "Optus Stadium", "short_name": "Optus", "abbrev": "OS"}, "ven1avg": 0, "ven2": {"id": 53, "name": "Perth Stadium", "display_name": "Optus Stadium", "short_name": "Optus", "abbrev": "OS"}, "ven2avg": 0, "ven3": {"id": 13, "name": "Melbourne Cricket Ground", "display_name": "MCG", "short_name": "MCG", "abbrev": "MCG"}, "ven3avg": 0, "trin": 0, "trinp": 0, "trout": 0, "troutp": 0, "adp": null, "adp_rank": null, "start": 80, "bench": 20, "ownr": 10, "owncr": 1, "owncsr": -19, "livepts": 0, "livegames": 0, "owned": 0.225564, "ppts": 22, "points_per_min": null, "total_points_per_min": null, "mvp_value": null, "position_change": -4, "hot": false, "cold": false, "phot": false, "pcold": false, "position_ranks": [{"pos_rank": "69", "pos_rd_rank": "60", "pos_rank_pos": "RUC"}]}, {"player_id": 240, "round": 19, "points": 0, "price": 123900, "total_points": 0, "position": 643, "games": 0, "total_games": 0, "price_change": 0, "total_price_change": 0, "last_position": 635, "round_position": 414, "minutes_played": 0, "total_minutes_played": 0, "updated_at": "2024-07-21T10:21:55+10:00", "kicks": 0, "total_kicks": 0, "handballs": 0, "total_handballs": 0, "marks": 0, "total_marks": 0, "tackles": 0, "total_tackles": 0, "freekicks_for": 0, "total_freekicks_for": 0, "freekicks_against": 0, "total_freekicks_against": 0, "hitouts": 0, "total_hitouts": 0, "goals": 0, "total_goals": 0, "behinds": 0, "total_behinds": 0, "avg5": 0, "own_raw": 10, "status": "locked", "avg": 0, "std": null, "avg3": 0, "pavg3": 22, "ppts1": 22, "ppts2": 22, "ppts3": 22, "pmin": 22, "pmax": 22, "prange": "22-22", "be1": 24, "be2": 28, "be3": 28, "bp1": null, "bp2": null, "bp3": null, "pp1": 123900, "pp2": 123900, "pp3": 121100, "ppc1": 0, "ppc2": 0, "ppc3": -2800, "ppcs": -6500, "capt": 0, "vice": 0, "own": 0.248633, "ownc": 0.228149, "ownc3": 0.230098, "owncs": 0.183111, "opp": {"id": 10, "abbrev": "MEL", "name": "Melbourne", "opposition_ranking": [{"round": 19, "position": "DEF", "avg": 74.0892, "rank": 13, "team_id": 10}, {"round": 19, "position": "FWD", "avg": 64.3046, "rank": 14, "team_id": 10}, {"round": 19, "position": "MID", "avg": 80.2581, "rank": 15, "team_id": 10}, {"round": 19, "position": "RUC", "avg": 79.3448, "rank": 4, "team_id": 10}]}, "oppavg": 0, "opph": 0, "opp1": {"id": 16, "abbrev": "WCE", "name": "West Coast", "opposition_ranking": [{"round": 19, "position": "DEF", "avg": 76.2829, "rank": 16, "team_id": 16}, {"round": 19, "position": "FWD", "avg": 68.3641, "rank": 16, "team_id": 16}, {"round": 19, "position": "MID", "avg": 84.3091, "rank": 17, "team_id": 16}, {"round": 19, "position": "RUC", "avg": 107, "rank": 18, "team_id": 16}]}, "opp1avg": 0, "opp1h": 0, "opp2": {"id": 5, "abbrev": "ESS", "name": "Essendon", "opposition_ranking": [{"round": 19, "position": "DEF", "avg": 70.2134, "rank": 6, "team_id": 5}, {"round": 19, "position": "FWD", "avg": 60.0226, "rank": 5, "team_id": 5}, {"round": 19, "position": "MID", "avg": 75.2432, "rank": 7, "team_id": 5}, {"round": 19, "position": "RUC", "avg": 79, "rank": 3, "team_id": 5}]}, "opp2avg": 0, "opp2h": 1, "opp3": {"id": 7, "abbrev": "GEE", "name": "Geelong", "opposition_ranking": [{"round": 19, "position": "DEF", "avg": 69.2857, "rank": 4, "team_id": 7}, {"round": 19, "position": "FWD", "avg": 64.4868, "rank": 15, "team_id": 7}, {"round": 19, "position": "MID", "avg": 78.465, "rank": 11, "team_id": 7}, {"round": 19, "position": "RUC", "avg": 99.0417, "rank": 17, "team_id": 7}]}, "opp3avg": 0, "opp3h": 0, "ven": {"id": 53, "name": "Perth Stadium", "display_name": "Optus Stadium", "short_name": "Optus", "abbrev": "OS"}, "venavg": 0, "ven1": {"id": 53, "name": "Perth Stadium", "display_name": "Optus Stadium", "short_name": "Optus", "abbrev": "OS"}, "ven1avg": 0, "ven2": {"id": 13, "name": "Melbourne Cricket Ground", "display_name": "MCG", "short_name": "MCG", "abbrev": "MCG"}, "ven2avg": 0, "ven3": {"id": 53, "name": "Perth Stadium", "display_name": "Optus Stadium", "short_name": "Optus", "abbrev": "OS"}, "ven3avg": 0, "trin": 0, "trinp": 0, "trout": 0, "troutp": 0, "adp": null, "adp_rank": null, "start": 80, "bench": 20, "ownr": 10, "owncr": 0, "owncsr": -19, "livepts": 0, "livegames": 0, "owned": 0.249563, "ppts": 22, "points_per_min": null, "total_points_per_min": null, "mvp_value": null, "position_change": -8, "hot": false, "cold": false, "phot": false, "pcold": false, "position_ranks": [{"pos_rank": "69", "pos_rd_rank": "45", "pos_rank_pos": "RUC"}]}, {"player_id": 240, "round": 20, "points": 0, "price": 123900, "total_points": 0, "position": 644, "games": 0, "total_games": 0, "price_change": 0, "total_price_change": 0, "last_position": 643, "round_position": 412, "minutes_played": 0, "total_minutes_played": 0, "updated_at": "2024-07-28T09:12:51+10:00", "kicks": 0, "total_kicks": 0, "handballs": 0, "total_handballs": 0, "marks": 0, "total_marks": 0, "tackles": 0, "total_tackles": 0, "freekicks_for": 0, "total_freekicks_for": 0, "freekicks_against": 0, "total_freekicks_against": 0, "hitouts": 0, "total_hitouts": 0, "goals": 0, "total_goals": 0, "behinds": 0, "total_behinds": 0, "avg5": 0, "own_raw": 10, "status": "locked", "avg": 0, "std": null, "avg3": 0, "pavg3": 22, "ppts1": 22, "ppts2": 22, "ppts3": 22, "pmin": 22, "pmax": 22, "prange": "22-22", "be1": 24, "be2": 29, "be3": 29, "bp1": null, "bp2": null, "bp3": null, "pp1": 123900, "pp2": 123900, "pp3": 120900, "ppc1": 0, "ppc2": 0, "ppc3": -3000, "ppcs": -5200, "capt": 0, "vice": 0, "own": 0.371655, "ownc": 0.351217, "ownc3": 0.353169, "owncs": 0.306133, "opp": {"id": 16, "abbrev": "WCE", "name": "West Coast", "opposition_ranking": [{"round": 20, "position": "DEF", "avg": 75.7143, "rank": 15, "team_id": 16}, {"round": 20, "position": "FWD", "avg": 68.5959, "rank": 17, "team_id": 16}, {"round": 20, "position": "MID", "avg": 84.4767, "rank": 17, "team_id": 16}, {"round": 20, "position": "RUC", "avg": 106.292, "rank": 18, "team_id": 16}]}, "oppavg": 0, "opph": 0, "opp1": {"id": 5, "abbrev": "ESS", "name": "Essendon", "opposition_ranking": [{"round": 20, "position": "DEF", "avg": 71.064, "rank": 7, "team_id": 5}, {"round": 20, "position": "FWD", "avg": 60.7043, "rank": 7, "team_id": 5}, {"round": 20, "position": "MID", "avg": 75.4268, "rank": 5, "team_id": 5}, {"round": 20, "position": "RUC", "avg": 81.24, "rank": 4, "team_id": 5}]}, "opp1avg": 0, "opp1h": 1, "opp2": {"id": 7, "abbrev": "GEE", "name": "Geelong", "opposition_ranking": [{"round": 20, "position": "DEF", "avg": 69.4194, "rank": 4, "team_id": 7}, {"round": 20, "position": "FWD", "avg": 64.404, "rank": 14, "team_id": 7}, {"round": 20, "position": "MID", "avg": 77.988, "rank": 11, "team_id": 7}, {"round": 20, "position": "RUC", "avg": 97.8462, "rank": 17, "team_id": 7}]}, "opp2avg": 0, "opp2h": 0, "opp3": {"id": 18, "abbrev": "GWS", "name": "GWS Giants", "opposition_ranking": [{"round": 20, "position": "DEF", "avg": 67.4294, "rank": 2, "team_id": 18}, {"round": 20, "position": "FWD", "avg": 59.0051, "rank": 3, "team_id": 18}, {"round": 20, "position": "MID", "avg": 76.6604, "rank": 9, "team_id": 18}, {"round": 20, "position": "RUC", "avg": 85.0357, "rank": 7, "team_id": 18}]}, "opp3avg": 0, "opp3h": 1, "ven": {"id": 53, "name": "Perth Stadium", "display_name": "Optus Stadium", "short_name": "Optus", "abbrev": "OS"}, "venavg": 0, "ven1": {"id": 13, "name": "Melbourne Cricket Ground", "display_name": "MCG", "short_name": "MCG", "abbrev": "MCG"}, "ven1avg": 0, "ven2": {"id": 53, "name": "Perth Stadium", "display_name": "Optus Stadium", "short_name": "Optus", "abbrev": "OS"}, "ven2avg": 0, "ven3": {"id": 17, "name": "Engie Stadium", "display_name": "Engie Stadium", "short_name": "Engie", "abbrev": "ENS"}, "ven3avg": 0, "trin": 5, "trinp": 0.0379248, "trout": 0, "troutp": 0, "adp": null, "adp_rank": null, "start": 60, "bench": 40, "ownr": 15, "owncr": 5, "owncsr": -14, "livepts": 0, "livegames": 0, "owned": 0.248633, "ppts": 22, "points_per_min": null, "total_points_per_min": null, "mvp_value": null, "position_change": -1, "hot": false, "cold": false, "phot": false, "pcold": false, "position_ranks": [{"pos_rank": "69", "pos_rd_rank": "61", "pos_rank_pos": "RUC"}]}, {"player_id": 240, "round": 21, "points": 0, "price": 123900, "total_points": 0, "position": 648, "games": 0, "total_games": 0, "price_change": 0, "total_price_change": 0, "last_position": 644, "round_position": 414, "minutes_played": 0, "total_minutes_played": 0, "updated_at": "2024-08-04T09:37:23+10:00", "kicks": 0, "total_kicks": 0, "handballs": 0, "total_handballs": 0, "marks": 0, "total_marks": 0, "tackles": 0, "total_tackles": 0, "freekicks_for": 0, "total_freekicks_for": 0, "freekicks_against": 0, "total_freekicks_against": 0, "hitouts": 0, "total_hitouts": 0, "goals": 0, "total_goals": 0, "behinds": 0, "total_behinds": 0, "avg5": 0, "own_raw": 15, "status": "locked", "avg": 0, "std": null, "avg3": 0, "pavg3": 22, "ppts1": 22, "ppts2": 22, "ppts3": 22, "pmin": 22, "pmax": 22, "prange": "22-22", "be1": 24, "be2": 29, "be3": 29, "bp1": null, "bp2": null, "bp3": null, "pp1": 123900, "pp2": 123900, "pp3": 121000, "ppc1": 0, "ppc2": 0, "ppc3": -2900, "ppcs": -2900, "capt": 0, "vice": 0, "own": 0.346792, "ownc": 0.316176, "ownc3": 0.326308, "owncs": 0.28127, "opp": {"id": 5, "abbrev": "ESS", "name": "Essendon", "opposition_ranking": [{"round": 21, "position": "DEF", "avg": 71.5028, "rank": 8, "team_id": 5}, {"round": 21, "position": "FWD", "avg": 60.4205, "rank": 7, "team_id": 5}, {"round": 21, "position": "MID", "avg": 75.4329, "rank": 5, "team_id": 5}, {"round": 21, "position": "RUC", "avg": 79.6667, "rank": 3, "team_id": 5}]}, "oppavg": 0, "opph": 1, "opp1": {"id": 7, "abbrev": "GEE", "name": "Geelong", "opposition_ranking": [{"round": 21, "position": "DEF", "avg": 68.9202, "rank": 3, "team_id": 7}, {"round": 21, "position": "FWD", "avg": 64.722, "rank": 15, "team_id": 7}, {"round": 21, "position": "MID", "avg": 77.4068, "rank": 11, "team_id": 7}, {"round": 21, "position": "RUC", "avg": 98.5556, "rank": 17, "team_id": 7}]}, "opp1avg": 0, "opp1h": 0, "opp2": {"id": 18, "abbrev": "GWS", "name": "GWS Giants", "opposition_ranking": [{"round": 21, "position": "DEF", "avg": 68.2905, "rank": 2, "team_id": 18}, {"round": 21, "position": "FWD", "avg": 58.8786, "rank": 4, "team_id": 18}, {"round": 21, "position": "MID", "avg": 76.509, "rank": 9, "team_id": 18}, {"round": 21, "position": "RUC", "avg": 85.8621, "rank": 8, "team_id": 18}]}, "opp2avg": 0, "opp2h": 1, "opp3": {"id": 11, "abbrev": "PTA", "name": "Port Adelaide", "opposition_ranking": [{"round": 21, "position": "DEF", "avg": 70.4663, "rank": 6, "team_id": 11}, {"round": 21, "position": "FWD", "avg": 60.12, "rank": 6, "team_id": 11}, {"round": 21, "position": "MID", "avg": 75.4651, "rank": 6, "team_id": 11}, {"round": 21, "position": "RUC", "avg": 82.3103, "rank": 6, "team_id": 11}]}, "opp3avg": 0, "opp3h": 0, "ven": {"id": 13, "name": "Melbourne Cricket Ground", "display_name": "MCG", "short_name": "MCG", "abbrev": "MCG"}, "venavg": 0, "ven1": {"id": 53, "name": "Perth Stadium", "display_name": "Optus Stadium", "short_name": "Optus", "abbrev": "OS"}, "ven1avg": 0, "ven2": {"id": 17, "name": "Engie Stadium", "display_name": "Engie Stadium", "short_name": "Engie", "abbrev": "ENS"}, "ven2avg": 0, "ven3": {"id": 53, "name": "Perth Stadium", "display_name": "Optus Stadium", "short_name": "Optus", "abbrev": "OS"}, "ven3avg": 0, "trin": 2, "trinp": 0.0168947, "trout": 1, "troutp": 0.00844737, "adp": null, "adp_rank": null, "start": 57.1429, "bench": 42.8571, "ownr": 14, "owncr": -1, "owncsr": -15, "livepts": 0, "livegames": 0, "owned": 0.371655, "ppts": 22, "points_per_min": null, "total_points_per_min": null, "mvp_value": null, "position_change": -4, "hot": false, "cold": false, "phot": false, "pcold": false, "position_ranks": [{"pos_rank": "62", "pos_rd_rank": "61", "pos_rank_pos": "RUC"}]}, {"player_id": 240, "round": 22, "points": 0, "price": 123900, "total_points": 0, "position": 651, "games": 0, "total_games": 0, "price_change": 0, "total_price_change": 0, "last_position": 648, "round_position": 414, "minutes_played": 0, "total_minutes_played": 0, "updated_at": "2024-08-11T09:40:30+10:00", "kicks": 0, "total_kicks": 0, "handballs": 0, "total_handballs": 0, "marks": 0, "total_marks": 0, "tackles": 0, "total_tackles": 0, "freekicks_for": 0, "total_freekicks_for": 0, "freekicks_against": 0, "total_freekicks_against": 0, "hitouts": 0, "total_hitouts": 0, "goals": 0, "total_goals": 0, "behinds": 0, "total_behinds": 0, "avg5": 0, "own_raw": 14, "status": "locked", "avg": 0, "std": null, "avg3": 0, "pavg3": 22, "ppts1": 22, "ppts2": 22, "ppts3": 22, "pmin": 22, "pmax": 22, "prange": "22-22", "be1": 24, "be2": 28, "be3": 28, "bp1": null, "bp2": null, "bp3": null, "pp1": 123900, "pp2": 123900, "pp3": 123900, "ppc1": 0, "ppc2": 0, "ppc3": 0, "ppcs": 0, "capt": 0, "vice": 0, "own": 1.53541, "ownc": 1.50686, "ownc3": 1.51496, "owncs": 1.46989, "opp": {"id": 7, "abbrev": "GEE", "name": "Geelong", "opposition_ranking": [{"round": 22, "position": "DEF", "avg": 70.3779, "rank": 6, "team_id": 7}, {"round": 22, "position": "FWD", "avg": 64.2009, "rank": 15, "team_id": 7}, {"round": 22, "position": "MID", "avg": 77.5543, "rank": 11, "team_id": 7}, {"round": 22, "position": "RUC", "avg": 97.9286, "rank": 17, "team_id": 7}]}, "oppavg": 0, "opph": 0, "opp1": {"id": 18, "abbrev": "GWS", "name": "GWS Giants", "opposition_ranking": [{"round": 22, "position": "DEF", "avg": 67.8486, "rank": 1, "team_id": 18}, {"round": 22, "position": "FWD", "avg": 59.4352, "rank": 4, "team_id": 18}, {"round": 22, "position": "MID", "avg": 76.8814, "rank": 9, "team_id": 18}, {"round": 22, "position": "RUC", "avg": 83.6774, "rank": 8, "team_id": 18}]}, "opp1avg": 0, "opp1h": 1, "opp2": {"id": 11, "abbrev": "PTA", "name": "Port Adelaide", "opposition_ranking": [{"round": 22, "position": "DEF", "avg": 70.1011, "rank": 5, "team_id": 11}, {"round": 22, "position": "FWD", "avg": 60.5142, "rank": 7, "team_id": 11}, {"round": 22, "position": "MID", "avg": 75.4494, "rank": 6, "team_id": 11}, {"round": 22, "position": "RUC", "avg": 85.4667, "rank": 9, "team_id": 11}]}, "opp2avg": 0, "opp2h": 0, "opp3": null, "opp3avg": 0, "opp3h": null, "ven": {"id": 53, "name": "Perth Stadium", "display_name": "Optus Stadium", "short_name": "Optus", "abbrev": "OS"}, "venavg": 0, "ven1": {"id": 17, "name": "Engie Stadium", "display_name": "Engie Stadium", "short_name": "Engie", "abbrev": "ENS"}, "ven1avg": 0, "ven2": {"id": 53, "name": "Perth Stadium", "display_name": "Optus Stadium", "short_name": "Optus", "abbrev": "OS"}, "ven2avg": 0, "ven3": null, "ven3avg": 0, "trin": 64, "trinp": 0.662389, "trout": 16, "troutp": 0.165597, "adp": null, "adp_rank": null, "start": 38.7097, "bench": 61.2903, "ownr": 62, "owncr": 48, "owncsr": 33, "livepts": 53, "livegames": 1, "owned": 0.346792, "ppts": 22, "points_per_min": null, "total_points_per_min": null, "mvp_value": null, "position_change": -3, "hot": false, "cold": false, "phot": false, "pcold": false, "position_ranks": [{"pos_rank": "62", "pos_rd_rank": "61", "pos_rank_pos": "RUC"}]}, {"player_id": 240, "round": 23, "points": 53, "price": 123900, "total_points": 53, "position": 624, "games": 1, "total_games": 1, "price_change": 0, "total_price_change": 0, "last_position": 651, "round_position": 295, "minutes_played": 91, "total_minutes_played": 91, "updated_at": "2024-08-18T09:48:09+10:00", "kicks": 2, "total_kicks": 2, "handballs": 4, "total_handballs": 4, "marks": 0, "total_marks": 0, "tackles": 2, "total_tackles": 2, "freekicks_for": 0, "total_freekicks_for": 0, "freekicks_against": 0, "total_freekicks_against": 0, "hitouts": 31, "total_hitouts": 31, "goals": 0, "total_goals": 0, "behinds": 0, "total_behinds": 0, "avg5": 53, "own_raw": 62, "status": "locked", "avg": 53, "std": null, "avg3": 53, "pavg3": 28, "ppts1": 28, "ppts2": 28, "ppts3": 28, "pmin": 28, "pmax": 28, "prange": "28-28", "be1": -3, "be2": -3, "be3": -3, "bp1": null, "bp2": null, "bp3": null, "pp1": 123900, "pp2": 123900, "pp3": 123900, "ppc1": 0, "ppc2": 0, "ppc3": 0, "ppcs": 0, "capt": 0, "vice": 0, "own": 1.43742, "ownc": 1.31104, "ownc3": 1.40681, "owncs": 1.3719, "opp": {"id": 18, "abbrev": "GWS", "name": "GWS Giants", "opposition_ranking": [{"round": 23, "position": "DEF", "avg": 67.5751, "rank": 1, "team_id": 18}, {"round": 23, "position": "FWD", "avg": 59.5893, "rank": 4, "team_id": 18}, {"round": 23, "position": "MID", "avg": 76.6054, "rank": 10, "team_id": 18}, {"round": 23, "position": "RUC", "avg": 82.7576, "rank": 6, "team_id": 18}]}, "oppavg": 53, "opph": 1, "opp1": {"id": 11, "abbrev": "PTA", "name": "Port Adelaide", "opposition_ranking": [{"round": 23, "position": "DEF", "avg": 70.2908, "rank": 4, "team_id": 11}, {"round": 23, "position": "FWD", "avg": 60.2466, "rank": 7, "team_id": 11}, {"round": 23, "position": "MID", "avg": 75.5508, "rank": 6, "team_id": 11}, {"round": 23, "position": "RUC", "avg": 84.7419, "rank": 9, "team_id": 11}]}, "opp1avg": 0, "opp1h": 0, "opp2": null, "opp2avg": 0, "opp2h": null, "opp3": null, "opp3avg": 0, "opp3h": null, "ven": {"id": 17, "name": "Engie Stadium", "display_name": "Engie Stadium", "short_name": "Engie", "abbrev": "ENS"}, "venavg": 53, "ven1": {"id": 53, "name": "Perth Stadium", "display_name": "Optus Stadium", "short_name": "Optus", "abbrev": "OS"}, "ven1avg": 0, "ven2": null, "ven2avg": 0, "ven3": null, "ven3avg": 0, "trin": 5, "trinp": 0.119303, "trout": 6, "troutp": 0.143164, "adp": null, "adp_rank": null, "start": 37.931, "bench": 62.069, "ownr": 58, "owncr": -4, "owncsr": 29, "livepts": 29, "livegames": 1, "owned": 1.53541, "ppts": 22, "points_per_min": 0.5824175824175825, "total_points_per_min": 0.5824175824175825, "mvp_value": 2337.735849056604, "position_change": 27, "hot": false, "cold": false, "phot": false, "pcold": false, "position_ranks": [{"pos_rank": "43", "pos_rd_rank": "23", "pos_rank_pos": "RUC"}]}, {"player_id": 240, "round": 24, "points": 29, "price": 123900, "total_points": 82, "position": 619, "games": 1, "total_games": 2, "price_change": 0, "total_price_change": 0, "last_position": 624, "round_position": 382, "minutes_played": 80, "total_minutes_played": 171, "updated_at": "2024-08-25T11:36:30+10:00", "kicks": 4, "total_kicks": 6, "handballs": 0, "total_handballs": 4, "marks": 0, "total_marks": 0, "tackles": 5, "total_tackles": 7, "freekicks_for": 2, "total_freekicks_for": 2, "freekicks_against": -1, "total_freekicks_against": -1, "hitouts": 19, "total_hitouts": 50, "goals": 0, "total_goals": 0, "behinds": 0, "total_behinds": 0, "avg5": 41, "own_raw": 58, "status": "none", "avg": 41, "std": null, "avg3": 41, "pavg3": 0, "ppts1": 28, "ppts2": 28, "ppts3": 28, "pmin": 28, "pmax": 28, "prange": "28-28", "be1": -3, "be2": -3, "be3": -3, "bp1": null, "bp2": null, "bp3": null, "pp1": 123900, "pp2": 123900, "pp3": 123900, "ppc1": 0, "ppc2": 0, "ppc3": 0, "ppcs": -123900, "capt": 0, "vice": 0, "own": 1.436, "ownc": 1.30986, "ownc3": 1.40538, "owncs": 1.37048, "opp": {"id": 11, "abbrev": "PTA", "name": "Port Adelaide", "opposition_ranking": [{"round": 24, "position": "DEF", "avg": 70.6274, "rank": 5, "team_id": 11}, {"round": 24, "position": "FWD", "avg": 60.2203, "rank": 8, "team_id": 11}, {"round": 24, "position": "MID", "avg": 75.8974, "rank": 7, "team_id": 11}, {"round": 24, "position": "RUC", "avg": 83.2121, "rank": 6, "team_id": 11}]}, "oppavg": 29, "opph": 0, "opp1": null, "opp1avg": 0, "opp1h": null, "opp2": null, "opp2avg": 0, "opp2h": null, "opp3": null, "opp3avg": 0, "opp3h": null, "ven": {"id": 53, "name": "Perth Stadium", "display_name": "Optus Stadium", "short_name": "Optus", "abbrev": "OS"}, "venavg": 29, "ven1": null, "ven1avg": 0, "ven2": null, "ven2avg": 0, "ven3": null, "ven3avg": 0, "trin": 5, "trinp": 0.119303, "trout": 6, "troutp": 0.143164, "adp": null, "adp_rank": null, "start": 37.931, "bench": 62.069, "ownr": 58, "owncr": -4, "owncsr": 29, "livepts": 0, "livegames": 0, "owned": 1.43742, "ppts": 28, "points_per_min": 0.3625, "total_points_per_min": 0.47953216374269003, "mvp_value": 3021.951219512195, "position_change": 5, "hot": false, "cold": false, "phot": false, "pcold": false, "position_ranks": [{"pos_rank": "43", "pos_rd_rank": "26", "pos_rank_pos": "RUC"}]}, {"player_id": 240, "round": 25, "points": 0, "price": 123900, "total_points": 82, "position": 0, "games": 0, "total_games": 2, "price_change": 0, "total_price_change": 0, "last_position": 619, "round_position": 0, "minutes_played": 0, "total_minutes_played": 171, "updated_at": "2024-08-25T11:37:49+10:00", "kicks": 0, "total_kicks": 6, "handballs": 0, "total_handballs": 4, "marks": 0, "total_marks": 0, "tackles": 0, "total_tackles": 7, "freekicks_for": 0, "total_freekicks_for": 2, "freekicks_against": 0, "total_freekicks_against": -1, "hitouts": 0, "total_hitouts": 50, "goals": 0, "total_goals": 0, "behinds": 0, "total_behinds": 0, "avg5": 41, "own_raw": 57, "status": "none", "avg": 41, "std": null, "avg3": 41, "pavg3": 0, "ppts1": null, "ppts2": null, "ppts3": null, "pmin": 0, "pmax": 0, "prange": "0-0", "be1": null, "be2": null, "be3": null, "bp1": null, "bp2": null, "bp3": null, "pp1": null, "pp2": null, "pp3": null, "ppc1": -123900, "ppc2": 0, "ppc3": 0, "ppcs": -123900, "capt": 0, "vice": 0, "own": 1.436, "ownc": 1.30986, "ownc3": 1.40538, "owncs": 1.37048, "opp": null, "oppavg": null, "opph": null, "opp1": null, "opp1avg": 0, "opp1h": null, "opp2": null, "opp2avg": 0, "opp2h": null, "opp3": null, "opp3avg": 0, "opp3h": null, "ven": null, "venavg": 0, "ven1": null, "ven1avg": 0, "ven2": null, "ven2avg": 0, "ven3": null, "ven3avg": 0, "trin": 5, "trinp": 0.119303, "trout": 6, "troutp": 0.143164, "adp": null, "adp_rank": null, "start": 37.931, "bench": 62.069, "ownr": 58, "owncr": -4, "owncsr": 29, "livepts": null, "livegames": null, "owned": 1.436, "ppts": 28, "points_per_min": null, "total_points_per_min": 0.47953216374269003, "mvp_value": 3021.951219512195, "position_change": null, "hot": false, "cold": false, "phot": false, "pcold": false}], "positions": [{"position": "RUC", "position_long": "Ruck", "sort": 3}], "notes": []}